{
"meta":{"test_sets":[],"test_metrics":[],"learn_metrics":[{"best_value":"Min","name":"Logloss"}],"launch_mode":"Train","parameters":"","iteration_count":1000,"learn_sets":["learn"],"name":"experiment"},
"iterations":[
{"learn":[0.6867708277],"iteration":0,"passed_time":0.14263876,"remaining_time":142.4961213},
{"learn":[0.6810867875],"iteration":1,"passed_time":0.1445327934,"remaining_time":72.12186393},
{"learn":[0.6741506788],"iteration":2,"passed_time":0.1461530147,"remaining_time":48.57151855},
{"learn":[0.6679284838],"iteration":3,"passed_time":0.1479989942,"remaining_time":36.85174955},
{"learn":[0.660869881],"iteration":4,"passed_time":0.1495145652,"remaining_time":29.75339847},
{"learn":[0.6544863383],"iteration":5,"passed_time":0.1511354515,"remaining_time":25.03810647},
{"learn":[0.6475731179],"iteration":6,"passed_time":0.152693576,"remaining_time":21.66067442},
{"learn":[0.6422049911],"iteration":7,"passed_time":0.1547059186,"remaining_time":19.18353391},
{"learn":[0.6366759406],"iteration":8,"passed_time":0.1562536277,"remaining_time":17.20526056},
{"learn":[0.632902216],"iteration":9,"passed_time":0.1576428669,"remaining_time":15.60664382},
{"learn":[0.6274360374],"iteration":10,"passed_time":0.1591544693,"remaining_time":14.30943364},
{"learn":[0.6239056057],"iteration":11,"passed_time":0.1609475159,"remaining_time":13.25134548},
{"learn":[0.6176276737],"iteration":12,"passed_time":0.1623078357,"remaining_time":12.3229103},
{"learn":[0.6128950472],"iteration":13,"passed_time":0.163711148,"remaining_time":11.52994228},
{"learn":[0.608559997],"iteration":14,"passed_time":0.1651225304,"remaining_time":10.84304616},
{"learn":[0.6029267488],"iteration":15,"passed_time":0.1666906311,"remaining_time":10.25147382},
{"learn":[0.597934299],"iteration":16,"passed_time":0.1684526747,"remaining_time":9.740528192},
{"learn":[0.5936531491],"iteration":17,"passed_time":0.1694429067,"remaining_time":9.24405191},
{"learn":[0.5882240578],"iteration":18,"passed_time":0.1709029999,"remaining_time":8.823991732},
{"learn":[0.5825475763],"iteration":19,"passed_time":0.1722703182,"remaining_time":8.441245593},
{"learn":[0.5771984524],"iteration":20,"passed_time":0.1740752628,"remaining_time":8.115222968},
{"learn":[0.5720363193],"iteration":21,"passed_time":0.1758553882,"remaining_time":7.817571347},
{"learn":[0.5685408557],"iteration":22,"passed_time":0.1773547196,"remaining_time":7.533720047},
{"learn":[0.5638903865],"iteration":23,"passed_time":0.1786961152,"remaining_time":7.266975351},
{"learn":[0.5587799637],"iteration":24,"passed_time":0.1803787552,"remaining_time":7.034771454},
{"learn":[0.5540889457],"iteration":25,"passed_time":0.1822244796,"remaining_time":6.82640935},
{"learn":[0.5498004489],"iteration":26,"passed_time":0.1837522996,"remaining_time":6.621888426},
{"learn":[0.5454131232],"iteration":27,"passed_time":0.1852839423,"remaining_time":6.431999713},
{"learn":[0.541676486],"iteration":28,"passed_time":0.186964332,"remaining_time":6.260081598},
{"learn":[0.537430516],"iteration":29,"passed_time":0.1888318416,"remaining_time":6.105562878},
{"learn":[0.5333731263],"iteration":30,"passed_time":0.1904624738,"remaining_time":5.953488294},
{"learn":[0.528873373],"iteration":31,"passed_time":0.1920595272,"remaining_time":5.809800698},
{"learn":[0.5242768747],"iteration":32,"passed_time":0.1938351716,"remaining_time":5.679957906},
{"learn":[0.5198363551],"iteration":33,"passed_time":0.1954333548,"remaining_time":5.552606492},
{"learn":[0.5166205653],"iteration":34,"passed_time":0.1969489142,"remaining_time":5.430162919},
{"learn":[0.5118062408],"iteration":35,"passed_time":0.1986335543,"remaining_time":5.318965175},
{"learn":[0.5083698343],"iteration":36,"passed_time":0.2004735616,"remaining_time":5.217730807},
{"learn":[0.5051282247],"iteration":37,"passed_time":0.2020861131,"remaining_time":5.115969496},
{"learn":[0.5015857838],"iteration":38,"passed_time":0.2034621235,"remaining_time":5.013515402},
{"learn":[0.4982378571],"iteration":39,"passed_time":0.204917594,"remaining_time":4.918022255},
{"learn":[0.4946177094],"iteration":40,"passed_time":0.2064931748,"remaining_time":4.829925722},
{"learn":[0.4914940728],"iteration":41,"passed_time":0.2081797954,"remaining_time":4.748482},
{"learn":[0.4878626929],"iteration":42,"passed_time":0.2097809496,"remaining_time":4.668845785},
{"learn":[0.4839720196],"iteration":43,"passed_time":0.2112974398,"remaining_time":4.590917101},
{"learn":[0.4805498123],"iteration":44,"passed_time":0.2127550233,"remaining_time":4.515134384},
{"learn":[0.4771551909],"iteration":45,"passed_time":0.214379356,"remaining_time":4.446041427},
{"learn":[0.4736452809],"iteration":46,"passed_time":0.2157874465,"remaining_time":4.37543482},
{"learn":[0.4702351182],"iteration":47,"passed_time":0.2172110489,"remaining_time":4.308019136},
{"learn":[0.4667283164],"iteration":48,"passed_time":0.2186685762,"remaining_time":4.243955428},
{"learn":[0.4646833914],"iteration":49,"passed_time":0.2203826501,"remaining_time":4.187270353},
{"learn":[0.4615431185],"iteration":50,"passed_time":0.2219520588,"remaining_time":4.130049094},
{"learn":[0.4584487986],"iteration":51,"passed_time":0.2233968067,"remaining_time":4.072695629},
{"learn":[0.4550429097],"iteration":52,"passed_time":0.224800872,"remaining_time":4.016725016},
{"learn":[0.4519139043],"iteration":53,"passed_time":0.226357068,"remaining_time":3.965440487},
{"learn":[0.4483303141],"iteration":54,"passed_time":0.228292502,"remaining_time":3.922480262},
{"learn":[0.4457028354],"iteration":55,"passed_time":0.2298268743,"remaining_time":3.874224453},
{"learn":[0.4426083741],"iteration":56,"passed_time":0.2312961733,"remaining_time":3.826531428},
{"learn":[0.4396195588],"iteration":57,"passed_time":0.2329578579,"remaining_time":3.783556933},
{"learn":[0.4362769657],"iteration":58,"passed_time":0.234912211,"remaining_time":3.746650688},
{"learn":[0.4338828899],"iteration":59,"passed_time":0.236442289,"remaining_time":3.704262528},
{"learn":[0.4313023532],"iteration":60,"passed_time":0.237926898,"remaining_time":3.662514054},
{"learn":[0.4284394582],"iteration":61,"passed_time":0.2394777832,"remaining_time":3.623067107},
{"learn":[0.4254697517],"iteration":62,"passed_time":0.2413817697,"remaining_time":3.590074892},
{"learn":[0.4227142334],"iteration":63,"passed_time":0.243283741,"remaining_time":3.558024712},
{"learn":[0.4195997097],"iteration":64,"passed_time":0.2448344289,"remaining_time":3.521849093},
{"learn":[0.4172705544],"iteration":65,"passed_time":0.2465624067,"remaining_time":3.489231634},
{"learn":[0.4144750171],"iteration":66,"passed_time":0.2483213204,"remaining_time":3.457967044},
{"learn":[0.4109356138],"iteration":67,"passed_time":0.2500501434,"remaining_time":3.427157848},
{"learn":[0.4084440867],"iteration":68,"passed_time":0.2515559809,"remaining_time":3.394182872},
{"learn":[0.4061484867],"iteration":69,"passed_time":0.2533900408,"remaining_time":3.366467685},
{"learn":[0.4037603096],"iteration":70,"passed_time":0.2553132097,"remaining_time":3.340647491},
{"learn":[0.4016093148],"iteration":71,"passed_time":0.2569475277,"remaining_time":3.311768135},
{"learn":[0.3991484465],"iteration":72,"passed_time":0.2585268754,"remaining_time":3.282937171},
{"learn":[0.3967635543],"iteration":73,"passed_time":0.2604179621,"remaining_time":3.258743688},
{"learn":[0.3941961924],"iteration":74,"passed_time":0.2618372195,"remaining_time":3.229325707},
{"learn":[0.3919507486],"iteration":75,"passed_time":0.2633577091,"remaining_time":3.201875305},
{"learn":[0.3897491738],"iteration":76,"passed_time":0.2648227809,"remaining_time":3.174434114},
{"learn":[0.3876819611],"iteration":77,"passed_time":0.2668468065,"remaining_time":3.154266097},
{"learn":[0.3853326727],"iteration":78,"passed_time":0.2683593445,"remaining_time":3.128594383},
{"learn":[0.3836838758],"iteration":79,"passed_time":0.2698527227,"remaining_time":3.103306311},
{"learn":[0.3812847137],"iteration":80,"passed_time":0.2713508459,"remaining_time":3.078659597},
{"learn":[0.3789600796],"iteration":81,"passed_time":0.2732467235,"remaining_time":3.059030393},
{"learn":[0.3764071994],"iteration":82,"passed_time":0.2749950033,"remaining_time":3.038197808},
{"learn":[0.3743778511],"iteration":83,"passed_time":0.2764958204,"remaining_time":3.015121089},
{"learn":[0.372552024],"iteration":84,"passed_time":0.2779373586,"remaining_time":2.991913919},
{"learn":[0.3704406597],"iteration":85,"passed_time":0.2798563428,"remaining_time":2.974287178},
{"learn":[0.3686060376],"iteration":86,"passed_time":0.2814361182,"remaining_time":2.953461793},
{"learn":[0.3663595694],"iteration":87,"passed_time":0.282808773,"remaining_time":2.930927284},
{"learn":[0.3637972938],"iteration":88,"passed_time":0.2841471747,"remaining_time":2.908517709},
{"learn":[0.3616169117],"iteration":89,"passed_time":0.2858067037,"remaining_time":2.889823337},
{"learn":[0.3593921308],"iteration":90,"passed_time":0.2875253452,"remaining_time":2.872093833},
{"learn":[0.3574391824],"iteration":91,"passed_time":0.2888683737,"remaining_time":2.851005254},
{"learn":[0.3556928281],"iteration":92,"passed_time":0.2902498987,"remaining_time":2.830716754},
{"learn":[0.3542727011],"iteration":93,"passed_time":0.2917026721,"remaining_time":2.811517244},
{"learn":[0.3525907022],"iteration":94,"passed_time":0.2933442341,"remaining_time":2.794489809},
{"learn":[0.3505033564],"iteration":95,"passed_time":0.2947915838,"remaining_time":2.77595408},
{"learn":[0.3487821508],"iteration":96,"passed_time":0.2961439756,"remaining_time":2.756886701},
{"learn":[0.3461545662],"iteration":97,"passed_time":0.2974161436,"remaining_time":2.737442465},
{"learn":[0.3445394304],"iteration":98,"passed_time":0.2993247754,"remaining_time":2.724157805},
{"learn":[0.3425844687],"iteration":99,"passed_time":0.3010333632,"remaining_time":2.709300269},
{"learn":[0.3413872189],"iteration":100,"passed_time":0.3026846101,"remaining_time":2.694192718},
{"learn":[0.3399051737],"iteration":101,"passed_time":0.3040611513,"remaining_time":2.676930529},
{"learn":[0.3385940128],"iteration":102,"passed_time":0.3058063574,"remaining_time":2.663187404},
{"learn":[0.336566925],"iteration":103,"passed_time":0.3072463472,"remaining_time":2.647045453},
{"learn":[0.3353195544],"iteration":104,"passed_time":0.3085514053,"remaining_time":2.630033408},
{"learn":[0.3337152269],"iteration":105,"passed_time":0.309869794,"remaining_time":2.61343015},
{"learn":[0.3317544019],"iteration":106,"passed_time":0.3112450201,"remaining_time":2.597586944},
{"learn":[0.3299797906],"iteration":107,"passed_time":0.3130694171,"remaining_time":2.585721482},
{"learn":[0.3284151996],"iteration":108,"passed_time":0.3144186896,"remaining_time":2.570156445},
{"learn":[0.3269685109],"iteration":109,"passed_time":0.3157232731,"remaining_time":2.5544883},
{"learn":[0.3254461642],"iteration":110,"passed_time":0.3172352412,"remaining_time":2.540739905},
{"learn":[0.3241957205],"iteration":111,"passed_time":0.3189762187,"remaining_time":2.529025734},
{"learn":[0.3224699586],"iteration":112,"passed_time":0.3204886061,"remaining_time":2.515693748},
{"learn":[0.3210817973],"iteration":113,"passed_time":0.321845471,"remaining_time":2.501360415},
{"learn":[0.3193155924],"iteration":114,"passed_time":0.3233334815,"remaining_time":2.48826201},
{"learn":[0.3177779162],"iteration":115,"passed_time":0.3249639582,"remaining_time":2.476449475},
{"learn":[0.3164694044],"iteration":116,"passed_time":0.3267461192,"remaining_time":2.465955755},
{"learn":[0.3150520325],"iteration":117,"passed_time":0.3280901909,"remaining_time":2.452335156},
{"learn":[0.3138932122],"iteration":118,"passed_time":0.329383563,"remaining_time":2.438545538},
{"learn":[0.3123903628],"iteration":119,"passed_time":0.3306824223,"remaining_time":2.42500443},
{"learn":[0.3109365039],"iteration":120,"passed_time":0.3327361365,"remaining_time":2.417149289},
{"learn":[0.3091697693],"iteration":121,"passed_time":0.3346142986,"remaining_time":2.408125854},
{"learn":[0.3076036595],"iteration":122,"passed_time":0.3363308767,"remaining_time":2.398066495},
{"learn":[0.3064058092],"iteration":123,"passed_time":0.3378312441,"remaining_time":2.386614273},
{"learn":[0.3053593812],"iteration":124,"passed_time":0.3393323465,"remaining_time":2.375326425},
{"learn":[0.3036053975],"iteration":125,"passed_time":0.3408163158,"remaining_time":2.364075079},
{"learn":[0.3020314817],"iteration":126,"passed_time":0.345733755,"remaining_time":2.376579277},
{"learn":[0.3008559898],"iteration":127,"passed_time":0.3484688091,"remaining_time":2.373943762},
{"learn":[0.2991510674],"iteration":128,"passed_time":0.3512103806,"remaining_time":2.371350709},
{"learn":[0.2980151353],"iteration":129,"passed_time":0.3542583516,"remaining_time":2.370805891},
{"learn":[0.2965271561],"iteration":130,"passed_time":0.356403881,"remaining_time":2.364236432},
{"learn":[0.2953127402],"iteration":131,"passed_time":0.3593363825,"remaining_time":2.36290894},
{"learn":[0.2940549674],"iteration":132,"passed_time":0.361652001,"remaining_time":2.357535976},
{"learn":[0.2925901766],"iteration":133,"passed_time":0.364650991,"remaining_time":2.356625061},
{"learn":[0.2915880062],"iteration":134,"passed_time":0.3681561207,"remaining_time":2.358926255},
{"learn":[0.2901075681],"iteration":135,"passed_time":0.3705093534,"remaining_time":2.353824127},
{"learn":[0.2885397452],"iteration":136,"passed_time":0.3727658744,"remaining_time":2.348152917},
{"learn":[0.2873697457],"iteration":137,"passed_time":0.3747046986,"remaining_time":2.340546741},
{"learn":[0.285997532],"iteration":138,"passed_time":0.3763045319,"remaining_time":2.330922316},
{"learn":[0.2849732505],"iteration":139,"passed_time":0.3784583688,"remaining_time":2.324815694},
{"learn":[0.2840769379],"iteration":140,"passed_time":0.381015133,"remaining_time":2.321219853},
{"learn":[0.2828309801],"iteration":141,"passed_time":0.383264935,"remaining_time":2.315783903},
{"learn":[0.2815663373],"iteration":142,"passed_time":0.3858027318,"remaining_time":2.31211847},
{"learn":[0.2807002421],"iteration":143,"passed_time":0.387481856,"remaining_time":2.303364366},
{"learn":[0.2801149156],"iteration":144,"passed_time":0.3890274735,"remaining_time":2.293920619},
{"learn":[0.2790430563],"iteration":145,"passed_time":0.3910608103,"remaining_time":2.287437891},
{"learn":[0.2779063295],"iteration":146,"passed_time":0.3925491921,"remaining_time":2.277853475},
{"learn":[0.2769645762],"iteration":147,"passed_time":0.3938988133,"remaining_time":2.267579655},
{"learn":[0.2753249981],"iteration":148,"passed_time":0.3952457364,"remaining_time":2.257410213},
{"learn":[0.2743099001],"iteration":149,"passed_time":0.3966168138,"remaining_time":2.247495278},
{"learn":[0.2730497784],"iteration":150,"passed_time":0.3985828646,"remaining_time":2.241038755},
{"learn":[0.2721064885],"iteration":151,"passed_time":0.4001789892,"remaining_time":2.232577518},
{"learn":[0.2711647175],"iteration":152,"passed_time":0.4015206163,"remaining_time":2.222797137},
{"learn":[0.2700823855],"iteration":153,"passed_time":0.4030052236,"remaining_time":2.213911813},
{"learn":[0.2689094897],"iteration":154,"passed_time":0.4047770134,"remaining_time":2.206687589},
{"learn":[0.2679061536],"iteration":155,"passed_time":0.4063001939,"remaining_time":2.198188228},
{"learn":[0.2669147209],"iteration":156,"passed_time":0.407802523,"remaining_time":2.189665776},
{"learn":[0.2662739224],"iteration":157,"passed_time":0.4091736415,"remaining_time":2.18053295},
{"learn":[0.2653854688],"iteration":158,"passed_time":0.4110667879,"remaining_time":2.174258922},
{"learn":[0.2645119561],"iteration":159,"passed_time":0.4126784739,"remaining_time":2.166561988},
{"learn":[0.263745202],"iteration":160,"passed_time":0.4141748621,"remaining_time":2.158339809},
{"learn":[0.2625196245],"iteration":161,"passed_time":0.4156546344,"remaining_time":2.150114714},
{"learn":[0.2614157641],"iteration":162,"passed_time":0.4174080448,"remaining_time":2.143377506},
{"learn":[0.2603798442],"iteration":163,"passed_time":0.4189572655,"remaining_time":2.135660207},
{"learn":[0.2591109099],"iteration":164,"passed_time":0.4203926203,"remaining_time":2.127441442},
{"learn":[0.2581357426],"iteration":165,"passed_time":0.4217761388,"remaining_time":2.119043974},
{"learn":[0.2569203907],"iteration":166,"passed_time":0.4232567069,"remaining_time":2.111214592},
{"learn":[0.2558265969],"iteration":167,"passed_time":0.4249864913,"remaining_time":2.104695004},
{"learn":[0.2549346288],"iteration":168,"passed_time":0.4265468202,"remaining_time":2.097398861},
{"learn":[0.2540545817],"iteration":169,"passed_time":0.4280535916,"remaining_time":2.089908712},
{"learn":[0.2529447697],"iteration":170,"passed_time":0.42939302,"remaining_time":2.081677272},
{"learn":[0.2523243516],"iteration":171,"passed_time":0.4312815043,"remaining_time":2.076169102},
{"learn":[0.2514063517],"iteration":172,"passed_time":0.432731006,"remaining_time":2.068604289},
{"learn":[0.2504387255],"iteration":173,"passed_time":0.4340383142,"remaining_time":2.060434756},
{"learn":[0.2495102706],"iteration":174,"passed_time":0.4355088571,"remaining_time":2.053113183},
{"learn":[0.248479384],"iteration":175,"passed_time":0.4372828151,"remaining_time":2.047278634},
{"learn":[0.2474232426],"iteration":176,"passed_time":0.4386882689,"remaining_time":2.039776527},
{"learn":[0.2462819771],"iteration":177,"passed_time":0.4401446229,"remaining_time":2.032577978},
{"learn":[0.2454883081],"iteration":178,"passed_time":0.441484441,"remaining_time":2.024909084},
{"learn":[0.2447263223],"iteration":179,"passed_time":0.4429178892,"remaining_time":2.017737051},
{"learn":[0.2440599512],"iteration":180,"passed_time":0.4445548062,"remaining_time":2.011549096},
{"learn":[0.2432442065],"iteration":181,"passed_time":0.4462431636,"remaining_time":2.00564235},
{"learn":[0.2423865354],"iteration":182,"passed_time":0.4477797417,"remaining_time":1.999104093},
{"learn":[0.241830349],"iteration":183,"passed_time":0.4490883246,"remaining_time":1.991609092},
{"learn":[0.2405583417],"iteration":184,"passed_time":0.4509751619,"remaining_time":1.986728416},
{"learn":[0.2398774359],"iteration":185,"passed_time":0.4524180758,"remaining_time":1.97993717},
{"learn":[0.2390813121],"iteration":186,"passed_time":0.4537651825,"remaining_time":1.972786596},
{"learn":[0.2383258254],"iteration":187,"passed_time":0.4550852171,"remaining_time":1.965580831},
{"learn":[0.2376681257],"iteration":188,"passed_time":0.4567428875,"remaining_time":1.959886147},
{"learn":[0.2365285026],"iteration":189,"passed_time":0.4586334863,"remaining_time":1.955226968},
{"learn":[0.2355886035],"iteration":190,"passed_time":0.4600781461,"remaining_time":1.948707959},
{"learn":[0.2350791295],"iteration":191,"passed_time":0.46141873,"remaining_time":1.941803822},
{"learn":[0.2340823809],"iteration":192,"passed_time":0.4629006828,"remaining_time":1.935548451},
{"learn":[0.233059159],"iteration":193,"passed_time":0.4646799126,"remaining_time":1.930577369},
{"learn":[0.2322264777],"iteration":194,"passed_time":0.4663954725,"remaining_time":1.925376181},
{"learn":[0.2314765718],"iteration":195,"passed_time":0.4678410984,"remaining_time":1.919103281},
{"learn":[0.2302976184],"iteration":196,"passed_time":0.4694274429,"remaining_time":1.913452978},
{"learn":[0.2297960387],"iteration":197,"passed_time":0.471207658,"remaining_time":1.908628999},
{"learn":[0.2287238439],"iteration":198,"passed_time":0.4725868514,"remaining_time":1.902221447},
{"learn":[0.2278811137],"iteration":199,"passed_time":0.4739240735,"remaining_time":1.895696294},
{"learn":[0.227111163],"iteration":200,"passed_time":0.4752544612,"remaining_time":1.889195595},
{"learn":[0.2263324172],"iteration":201,"passed_time":0.4769957024,"remaining_time":1.884369161},
{"learn":[0.2253268383],"iteration":202,"passed_time":0.4783456154,"remaining_time":1.878036726},
{"learn":[0.2244210596],"iteration":203,"passed_time":0.479783088,"remaining_time":1.872094794},
{"learn":[0.2237718017],"iteration":204,"passed_time":0.4812994618,"remaining_time":1.866502791},
{"learn":[0.223069085],"iteration":205,"passed_time":0.4827823564,"remaining_time":1.860821315},
{"learn":[0.2223466944],"iteration":206,"passed_time":0.4843059026,"remaining_time":1.855336139},
{"learn":[0.2215950754],"iteration":207,"passed_time":0.4856515011,"remaining_time":1.849211485},
{"learn":[0.220868923],"iteration":208,"passed_time":0.4870880915,"remaining_time":1.84347694},
{"learn":[0.2203318101],"iteration":209,"passed_time":0.4884568664,"remaining_time":1.837528212},
{"learn":[0.2198367649],"iteration":210,"passed_time":0.490550962,"remaining_time":1.834335114},
{"learn":[0.2191487242],"iteration":211,"passed_time":0.4923354971,"remaining_time":1.830001753},
{"learn":[0.218199571],"iteration":212,"passed_time":0.493951884,"remaining_time":1.825071045},
{"learn":[0.2175748437],"iteration":213,"passed_time":0.4954652381,"remaining_time":1.819792884},
{"learn":[0.2168558262],"iteration":214,"passed_time":0.4974890825,"remaining_time":1.816413627},
{"learn":[0.2159265589],"iteration":215,"passed_time":0.4989311498,"remaining_time":1.810935284},
{"learn":[0.2151569967],"iteration":216,"passed_time":0.500276314,"remaining_time":1.805144488},
{"learn":[0.2144337407],"iteration":217,"passed_time":0.5016141273,"remaining_time":1.799368108},
{"learn":[0.2135953903],"iteration":218,"passed_time":0.5034072588,"remaining_time":1.795256024},
{"learn":[0.2131355074],"iteration":219,"passed_time":0.5049500252,"remaining_time":1.790277362},
{"learn":[0.2123903345],"iteration":220,"passed_time":0.5062533312,"remaining_time":1.784485724},
{"learn":[0.2116619393],"iteration":221,"passed_time":0.507591861,"remaining_time":1.778857963},
{"learn":[0.2110502808],"iteration":222,"passed_time":0.5088841981,"remaining_time":1.773107722},
{"learn":[0.2105814263],"iteration":223,"passed_time":0.5107198906,"remaining_time":1.769279621},
{"learn":[0.2096094555],"iteration":224,"passed_time":0.5123781292,"remaining_time":1.764858001},
{"learn":[0.2087342298],"iteration":225,"passed_time":0.5137619604,"remaining_time":1.75952105},
{"learn":[0.2079115797],"iteration":226,"passed_time":0.5150890384,"remaining_time":1.754025668},
{"learn":[0.2073449912],"iteration":227,"passed_time":0.5167430343,"remaining_time":1.749673783},
{"learn":[0.2067102856],"iteration":228,"passed_time":0.5182340731,"remaining_time":1.744796814},
{"learn":[0.2060932936],"iteration":229,"passed_time":0.519586856,"remaining_time":1.739486431},
{"learn":[0.2054648046],"iteration":230,"passed_time":0.5209725502,"remaining_time":1.734319875},
{"learn":[0.2048169595],"iteration":231,"passed_time":0.5223647409,"remaining_time":1.729207418},
{"learn":[0.2041914551],"iteration":232,"passed_time":0.5240845541,"remaining_time":1.725205378},
{"learn":[0.2037035624],"iteration":233,"passed_time":0.5255710419,"remaining_time":1.720459052},
{"learn":[0.2031964196],"iteration":234,"passed_time":0.5270906768,"remaining_time":1.715848373},
{"learn":[0.2027066902],"iteration":235,"passed_time":0.5284336296,"remaining_time":1.710691919},
{"learn":[0.2023374769],"iteration":236,"passed_time":0.530097131,"remaining_time":1.706599624},
{"learn":[0.2017354259],"iteration":237,"passed_time":0.5317261964,"remaining_time":1.702417486},
{"learn":[0.2014156271],"iteration":238,"passed_time":0.5332589313,"remaining_time":1.697949986},
{"learn":[0.2011964586],"iteration":239,"passed_time":0.5348172142,"remaining_time":1.693587845},
{"learn":[0.2007506688],"iteration":240,"passed_time":0.53640529,"remaining_time":1.689342801},
{"learn":[0.2001482292],"iteration":241,"passed_time":0.5379785755,"remaining_time":1.685073389},
{"learn":[0.1995742939],"iteration":242,"passed_time":0.539530724,"remaining_time":1.680760321},
{"learn":[0.1990204917],"iteration":243,"passed_time":0.5409115873,"remaining_time":1.67593918},
{"learn":[0.1983456435],"iteration":244,"passed_time":0.5424967968,"remaining_time":1.671775843},
{"learn":[0.1976327896],"iteration":245,"passed_time":0.5442239061,"remaining_time":1.668068395},
{"learn":[0.1970112235],"iteration":246,"passed_time":0.5456026467,"remaining_time":1.663314951},
{"learn":[0.1964426924],"iteration":247,"passed_time":0.5470071569,"remaining_time":1.658666863},
{"learn":[0.1959057737],"iteration":248,"passed_time":0.5484177266,"remaining_time":1.654063103},
{"learn":[0.1954597191],"iteration":249,"passed_time":0.5502157984,"remaining_time":1.650647395},
{"learn":[0.1947185552],"iteration":250,"passed_time":0.5516342451,"remaining_time":1.646111751},
{"learn":[0.1940575529],"iteration":251,"passed_time":0.5530114822,"remaining_time":1.641478527},
{"learn":[0.1934128337],"iteration":252,"passed_time":0.5543289373,"remaining_time":1.63669453},
{"learn":[0.1928152508],"iteration":253,"passed_time":0.5558127073,"remaining_time":1.632426298},
{"learn":[0.1924908073],"iteration":254,"passed_time":0.5578438694,"remaining_time":1.629779148},
{"learn":[0.1921357049],"iteration":255,"passed_time":0.559268319,"remaining_time":1.625373552},
{"learn":[0.1916299043],"iteration":256,"passed_time":0.5607569902,"remaining_time":1.621176824},
{"learn":[0.1909220307],"iteration":257,"passed_time":0.5622663199,"remaining_time":1.617060501},
{"learn":[0.1902517743],"iteration":258,"passed_time":0.5640256226,"remaining_time":1.613679484},
{"learn":[0.1900623816],"iteration":259,"passed_time":0.5653329466,"remaining_time":1.60902454},
{"learn":[0.1895168269],"iteration":260,"passed_time":0.5666280092,"remaining_time":1.604360532},
{"learn":[0.1889956086],"iteration":261,"passed_time":0.5680615344,"remaining_time":1.600112261},
{"learn":[0.1885263655],"iteration":262,"passed_time":0.5699676987,"remaining_time":1.597209863},
{"learn":[0.1878894523],"iteration":263,"passed_time":0.5714466781,"remaining_time":1.593124072},
{"learn":[0.1876827876],"iteration":264,"passed_time":0.5728535158,"remaining_time":1.588857865},
{"learn":[0.1872416426],"iteration":265,"passed_time":0.5742177526,"remaining_time":1.584495603},
{"learn":[0.1868074205],"iteration":266,"passed_time":0.575985098,"remaining_time":1.58126246},
{"learn":[0.1863031387],"iteration":267,"passed_time":0.5777805225,"remaining_time":1.578116949},
{"learn":[0.185788914],"iteration":268,"passed_time":0.5792570073,"remaining_time":1.574114767},
{"learn":[0.1852374253],"iteration":269,"passed_time":0.5806138342,"remaining_time":1.569807774},
{"learn":[0.1846649735],"iteration":270,"passed_time":0.5821079853,"remaining_time":1.565891961},
{"learn":[0.184196843],"iteration":271,"passed_time":0.5838306568,"remaining_time":1.562605581},
{"learn":[0.1838077086],"iteration":272,"passed_time":0.5851638747,"remaining_time":1.558293542},
{"learn":[0.183138918],"iteration":273,"passed_time":0.5866145203,"remaining_time":1.554314386},
{"learn":[0.1825773804],"iteration":274,"passed_time":0.5880812367,"remaining_time":1.550395988},
{"learn":[0.1820474907],"iteration":275,"passed_time":0.5902003023,"remaining_time":1.54820659},
{"learn":[0.18156366],"iteration":276,"passed_time":0.5917994479,"remaining_time":1.544660653},
{"learn":[0.1810967481],"iteration":277,"passed_time":0.5931428381,"remaining_time":1.540464493},
{"learn":[0.1805917599],"iteration":278,"passed_time":0.5944834768,"remaining_time":1.536281673},
{"learn":[0.1801097658],"iteration":279,"passed_time":0.5961865907,"remaining_time":1.533051233},
{"learn":[0.1797831677],"iteration":280,"passed_time":0.597707815,"remaining_time":1.52936626},
{"learn":[0.179081334],"iteration":281,"passed_time":0.5990319792,"remaining_time":1.525194897},
{"learn":[0.1786481186],"iteration":282,"passed_time":0.600336114,"remaining_time":1.520992911},
{"learn":[0.1781992382],"iteration":283,"passed_time":0.6019708795,"remaining_time":1.517644894},
{"learn":[0.1779410751],"iteration":284,"passed_time":0.6037968546,"remaining_time":1.5147886},
{"learn":[0.1776567742],"iteration":285,"passed_time":0.60516611,"remaining_time":1.51079931},
{"learn":[0.1770090527],"iteration":286,"passed_time":0.6065843916,"remaining_time":1.506950074},
{"learn":[0.1766137547],"iteration":287,"passed_time":0.6079992025,"remaining_time":1.50310914},
{"learn":[0.1759108084],"iteration":288,"passed_time":0.6100285516,"remaining_time":1.500796886},
{"learn":[0.1754384571],"iteration":289,"passed_time":0.6113613099,"remaining_time":1.496781138},
{"learn":[0.1749342989],"iteration":290,"passed_time":0.6126620795,"remaining_time":1.492705891},
{"learn":[0.17478187],"iteration":291,"passed_time":0.6140079793,"remaining_time":1.488759073},
{"learn":[0.1743167771],"iteration":292,"passed_time":0.6155703094,"remaining_time":1.485352248},
{"learn":[0.1737351947],"iteration":293,"passed_time":0.6175394811,"remaining_time":1.482934945},
{"learn":[0.1733983711],"iteration":294,"passed_time":0.61910907,"remaining_time":1.479565743},
{"learn":[0.1729208099],"iteration":295,"passed_time":0.6204996212,"remaining_time":1.475782883},
{"learn":[0.1723986025],"iteration":296,"passed_time":0.6220558113,"remaining_time":1.4724082},
{"learn":[0.1719780321],"iteration":297,"passed_time":0.6236561018,"remaining_time":1.469149609},
{"learn":[0.1715291694],"iteration":298,"passed_time":0.6249899615,"remaining_time":1.465277468},
{"learn":[0.1712462814],"iteration":299,"passed_time":0.6263201424,"remaining_time":1.461413666},
{"learn":[0.1708518134],"iteration":300,"passed_time":0.6276470114,"remaining_time":1.457559007},
{"learn":[0.1704524358],"iteration":301,"passed_time":0.6295259081,"remaining_time":1.454996966},
{"learn":[0.169962777],"iteration":302,"passed_time":0.6310045324,"remaining_time":1.451518677},
{"learn":[0.1695261708],"iteration":303,"passed_time":0.6323811304,"remaining_time":1.447819957},
{"learn":[0.1693100223],"iteration":304,"passed_time":0.6337672678,"remaining_time":1.4441582},
{"learn":[0.1689407561],"iteration":305,"passed_time":0.635534451,"remaining_time":1.44137552},
{"learn":[0.1685486546],"iteration":306,"passed_time":0.6372836157,"remaining_time":1.438558781},
{"learn":[0.1681753794],"iteration":307,"passed_time":0.6390713297,"remaining_time":1.435835585},
{"learn":[0.1678021219],"iteration":308,"passed_time":0.6405481152,"remaining_time":1.432423131},
{"learn":[0.1674531654],"iteration":309,"passed_time":0.6425813531,"remaining_time":1.430261721},
{"learn":[0.1671510449],"iteration":310,"passed_time":0.6442569114,"remaining_time":1.42730872},
{"learn":[0.1667798713],"iteration":311,"passed_time":0.6456384733,"remaining_time":1.423715608},
{"learn":[0.1663530844],"iteration":312,"passed_time":0.6470040922,"remaining_time":1.420101634},
{"learn":[0.1659275338],"iteration":313,"passed_time":0.6487812534,"remaining_time":1.417401082},
{"learn":[0.1655732614],"iteration":314,"passed_time":0.6506015595,"remaining_time":1.414800217},
{"learn":[0.1652001275],"iteration":315,"passed_time":0.6519656805,"remaining_time":1.411216853},
{"learn":[0.1650154149],"iteration":316,"passed_time":0.6532869597,"remaining_time":1.407555184},
{"learn":[0.1643735744],"iteration":317,"passed_time":0.6547542805,"remaining_time":1.404221444},
{"learn":[0.1639000222],"iteration":318,"passed_time":0.6564271795,"remaining_time":1.401338273},
{"learn":[0.163432969],"iteration":319,"passed_time":0.6577538615,"remaining_time":1.397726956},
{"learn":[0.1632452541],"iteration":320,"passed_time":0.6592658098,"remaining_time":1.39452176},
{"learn":[0.162690198],"iteration":321,"passed_time":0.6606160303,"remaining_time":1.390986548},
{"learn":[0.1621750019],"iteration":322,"passed_time":0.6624346155,"remaining_time":1.388446547},
{"learn":[0.1619211126],"iteration":323,"passed_time":0.6638096851,"remaining_time":1.384985639},
{"learn":[0.161492383],"iteration":324,"passed_time":0.665175815,"remaining_time":1.381519},
{"learn":[0.1610469465],"iteration":325,"passed_time":0.6664917111,"remaining_time":1.37796139},
{"learn":[0.1606769209],"iteration":326,"passed_time":0.6679711495,"remaining_time":1.374754078},
{"learn":[0.1600815455],"iteration":327,"passed_time":0.6697609107,"remaining_time":1.372193085},
{"learn":[0.1597209153],"iteration":328,"passed_time":0.671132984,"remaining_time":1.3687849},
{"learn":[0.1594916979],"iteration":329,"passed_time":0.6726376173,"remaining_time":1.365658193},
{"learn":[0.1591900366],"iteration":330,"passed_time":0.6741277012,"remaining_time":1.362511879},
{"learn":[0.1588244968],"iteration":331,"passed_time":0.6759385159,"remaining_time":1.360020869},
{"learn":[0.1585112148],"iteration":332,"passed_time":0.6773258266,"remaining_time":1.356685665},
{"learn":[0.1582141452],"iteration":333,"passed_time":0.6786647317,"remaining_time":1.353265603},
{"learn":[0.1578292847],"iteration":334,"passed_time":0.6799897761,"remaining_time":1.349830451},
{"learn":[0.1575032693],"iteration":335,"passed_time":0.6814775599,"remaining_time":1.346729464},
{"learn":[0.1570734801],"iteration":336,"passed_time":0.6832274551,"remaining_time":1.344153717},
{"learn":[0.1568049678],"iteration":337,"passed_time":0.6846867072,"remaining_time":1.34101361},
{"learn":[0.156467791],"iteration":338,"passed_time":0.6860301508,"remaining_time":1.33765761},
{"learn":[0.1562464502],"iteration":339,"passed_time":0.6874381047,"remaining_time":1.334438674},
{"learn":[0.1557068295],"iteration":340,"passed_time":0.6891632293,"remaining_time":1.331843308},
{"learn":[0.155231935],"iteration":341,"passed_time":0.6906198456,"remaining_time":1.328736428},
{"learn":[0.154867808],"iteration":342,"passed_time":0.6919823659,"remaining_time":1.325458934},
{"learn":[0.1544070244],"iteration":343,"passed_time":0.693309463,"remaining_time":1.322125023},
{"learn":[0.1540902279],"iteration":344,"passed_time":0.6950944632,"remaining_time":1.319672097},
{"learn":[0.1536753443],"iteration":345,"passed_time":0.6966531955,"remaining_time":1.316795346},
{"learn":[0.1533805706],"iteration":346,"passed_time":0.6979814043,"remaining_time":1.313492383},
{"learn":[0.1530993073],"iteration":347,"passed_time":0.6994142364,"remaining_time":1.310396788},
{"learn":[0.1527747931],"iteration":348,"passed_time":0.701197268,"remaining_time":1.307963958},
{"learn":[0.1524171299],"iteration":349,"passed_time":0.7030185005,"remaining_time":1.305605787},
{"learn":[0.1520075445],"iteration":350,"passed_time":0.7044582132,"remaining_time":1.302545243},
{"learn":[0.1519057839],"iteration":351,"passed_time":0.7058467151,"remaining_time":1.299399635},
{"learn":[0.1515591939],"iteration":352,"passed_time":0.7074284735,"remaining_time":1.296618194},
{"learn":[0.1510796017],"iteration":353,"passed_time":0.7091768358,"remaining_time":1.294147559},
{"learn":[0.1508387813],"iteration":354,"passed_time":0.7105623047,"remaining_time":1.291021652},
{"learn":[0.1505378617],"iteration":355,"passed_time":0.7119152746,"remaining_time":1.287846733},
{"learn":[0.15022571],"iteration":356,"passed_time":0.7132057069,"remaining_time":1.284569383},
{"learn":[0.149896763],"iteration":357,"passed_time":0.7151290841,"remaining_time":1.28243819},
{"learn":[0.1495790835],"iteration":358,"passed_time":0.7167748795,"remaining_time":1.279812529},
{"learn":[0.1494376571],"iteration":359,"passed_time":0.7186103967,"remaining_time":1.277529594},
{"learn":[0.1490803471],"iteration":360,"passed_time":0.7201204586,"remaining_time":1.274673055},
{"learn":[0.1487009614],"iteration":361,"passed_time":0.7223518394,"remaining_time":1.273095231},
{"learn":[0.1484347979],"iteration":362,"passed_time":0.7237199523,"remaining_time":1.269998925},
{"learn":[0.1481030517],"iteration":363,"passed_time":0.7250481974,"remaining_time":1.266842455},
{"learn":[0.1478240225],"iteration":364,"passed_time":0.7264122766,"remaining_time":1.263758344},
{"learn":[0.1473728727],"iteration":365,"passed_time":0.7281656052,"remaining_time":1.261357906},
{"learn":[0.1470510695],"iteration":366,"passed_time":0.7297064311,"remaining_time":1.258594471},
{"learn":[0.1467625477],"iteration":367,"passed_time":0.7310019026,"remaining_time":1.255416311},
{"learn":[0.1464855759],"iteration":368,"passed_time":0.7323528149,"remaining_time":1.252343161},
{"learn":[0.1462564468],"iteration":369,"passed_time":0.7339730687,"remaining_time":1.249737928},
{"learn":[0.1458629855],"iteration":370,"passed_time":0.7356733052,"remaining_time":1.247273609},
{"learn":[0.1456491152],"iteration":371,"passed_time":0.7372458332,"remaining_time":1.244597804},
{"learn":[0.1455043863],"iteration":372,"passed_time":0.7387128441,"remaining_time":1.241750545},
{"learn":[0.1452368807],"iteration":373,"passed_time":0.740016698,"remaining_time":1.238637575},
{"learn":[0.1449873006],"iteration":374,"passed_time":0.7419025956,"remaining_time":1.236504326},
{"learn":[0.144472599],"iteration":375,"passed_time":0.7435242011,"remaining_time":1.233933781},
{"learn":[0.1441380889],"iteration":376,"passed_time":0.7449706288,"remaining_time":1.231078785},
{"learn":[0.143910046],"iteration":377,"passed_time":0.746336495,"remaining_time":1.228098677},
{"learn":[0.1435676504],"iteration":378,"passed_time":0.748037386,"remaining_time":1.225676034},
{"learn":[0.1432500945],"iteration":379,"passed_time":0.7498700764,"remaining_time":1.22347223},
{"learn":[0.1428692341],"iteration":380,"passed_time":0.7513167096,"remaining_time":1.220643158},
{"learn":[0.1426287757],"iteration":381,"passed_time":0.7527180725,"remaining_time":1.217748086},
{"learn":[0.1424599047],"iteration":382,"passed_time":0.7543037693,"remaining_time":1.215157769},
{"learn":[0.1422020506],"iteration":383,"passed_time":0.7559210836,"remaining_time":1.212623405},
{"learn":[0.1417767737],"iteration":384,"passed_time":0.7572777756,"remaining_time":1.209677486},
{"learn":[0.1415738706],"iteration":385,"passed_time":0.758576276,"remaining_time":1.206647237},
{"learn":[0.1411975931],"iteration":386,"passed_time":0.7598799053,"remaining_time":1.203634062},
{"learn":[0.1407879017],"iteration":387,"passed_time":0.7616351288,"remaining_time":1.201342007},
{"learn":[0.1404900551],"iteration":388,"passed_time":0.7631468086,"remaining_time":1.19867018},
{"learn":[0.1401967473],"iteration":389,"passed_time":0.7646176658,"remaining_time":1.195940452},
{"learn":[0.1399648631],"iteration":390,"passed_time":0.7662450462,"remaining_time":1.193460954},
{"learn":[0.1397329525],"iteration":391,"passed_time":0.7682940356,"remaining_time":1.191639729},
{"learn":[0.1395382793],"iteration":392,"passed_time":0.7700525387,"remaining_time":1.189368679},
{"learn":[0.1393062539],"iteration":393,"passed_time":0.7714362609,"remaining_time":1.186523792},
{"learn":[0.138967726],"iteration":394,"passed_time":0.7727781435,"remaining_time":1.18362222},
{"learn":[0.1388613383],"iteration":395,"passed_time":0.7742695531,"remaining_time":1.180956591},
{"learn":[0.1384697843],"iteration":396,"passed_time":0.775994738,"remaining_time":1.178651957},
{"learn":[0.1381840529],"iteration":397,"passed_time":0.7772998119,"remaining_time":1.175714791},
{"learn":[0.1379600189],"iteration":398,"passed_time":0.778778905,"remaining_time":1.173047925},
{"learn":[0.1376237163],"iteration":399,"passed_time":0.7803544406,"remaining_time":1.170531661},
{"learn":[0.1374956855],"iteration":400,"passed_time":0.7824965491,"remaining_time":1.168866416},
{"learn":[0.1371247415],"iteration":401,"passed_time":0.7839075927,"remaining_time":1.166111295},
{"learn":[0.1368103999],"iteration":402,"passed_time":0.7853272874,"remaining_time":1.163375659},
{"learn":[0.1366347384],"iteration":403,"passed_time":0.7868129256,"remaining_time":1.160743821},
{"learn":[0.1362670528],"iteration":404,"passed_time":0.7887028938,"remaining_time":1.158711659},
{"learn":[0.136069545],"iteration":405,"passed_time":0.7900801159,"remaining_time":1.155930022},
{"learn":[0.1356998196],"iteration":406,"passed_time":0.7914135742,"remaining_time":1.153091522},
{"learn":[0.1353832086],"iteration":407,"passed_time":0.7928848116,"remaining_time":1.150460315},
{"learn":[0.1349141509],"iteration":408,"passed_time":0.7948394329,"remaining_time":1.148533264},
{"learn":[0.1345639052],"iteration":409,"passed_time":0.7964353198,"remaining_time":1.146089851},
{"learn":[0.1342667827],"iteration":410,"passed_time":0.7979296275,"remaining_time":1.143504989},
{"learn":[0.1338094429],"iteration":411,"passed_time":0.7994673047,"remaining_time":1.140987318},
{"learn":[0.1336536143],"iteration":412,"passed_time":0.801175237,"remaining_time":1.138716378},
{"learn":[0.1334642569],"iteration":413,"passed_time":0.8027494335,"remaining_time":1.13625886},
{"learn":[0.1331597258],"iteration":414,"passed_time":0.804318926,"remaining_time":1.133798968},
{"learn":[0.1330392272],"iteration":415,"passed_time":0.8060417321,"remaining_time":1.131558585},
{"learn":[0.1327072426],"iteration":416,"passed_time":0.8078905617,"remaining_time":1.129496876},
{"learn":[0.1324698042],"iteration":417,"passed_time":0.8098327223,"remaining_time":1.127566135},
{"learn":[0.1323372611],"iteration":418,"passed_time":0.8113759915,"remaining_time":1.125082222},
{"learn":[0.132175057],"iteration":419,"passed_time":0.8128129367,"remaining_time":1.12245596},
{"learn":[0.1318372532],"iteration":420,"passed_time":0.8147179013,"remaining_time":1.120479014},
{"learn":[0.1315739596],"iteration":421,"passed_time":0.8161007694,"remaining_time":1.11778731},
{"learn":[0.1311661226],"iteration":422,"passed_time":0.8174101194,"remaining_time":1.11500151},
{"learn":[0.1309066084],"iteration":423,"passed_time":0.818814717,"remaining_time":1.112352068},
{"learn":[0.1306715277],"iteration":424,"passed_time":0.8203938305,"remaining_time":1.109944594},
{"learn":[0.130440032],"iteration":425,"passed_time":0.8218099404,"remaining_time":1.107321375},
{"learn":[0.1301659566],"iteration":426,"passed_time":0.8232618816,"remaining_time":1.104751893},
{"learn":[0.1298405329],"iteration":427,"passed_time":0.8247032879,"remaining_time":1.102173553},
{"learn":[0.1295949088],"iteration":428,"passed_time":0.8262847734,"remaining_time":1.099786959},
{"learn":[0.1295078419],"iteration":429,"passed_time":0.8280295729,"remaining_time":1.097620597},
{"learn":[0.1293981693],"iteration":430,"passed_time":0.82944715,"remaining_time":1.095024196},
{"learn":[0.1293118265],"iteration":431,"passed_time":0.8308901136,"remaining_time":1.092466631},
{"learn":[0.1291559537],"iteration":432,"passed_time":0.832303656,"remaining_time":1.089875688},
{"learn":[0.1288762269],"iteration":433,"passed_time":0.8340304834,"remaining_time":1.087698741},
{"learn":[0.1284437798],"iteration":434,"passed_time":0.83556282,"remaining_time":1.085271249},
{"learn":[0.1281589932],"iteration":435,"passed_time":0.837211785,"remaining_time":1.082998731},
{"learn":[0.1278299932],"iteration":436,"passed_time":0.8388460896,"remaining_time":1.080710179},
{"learn":[0.1276037958],"iteration":437,"passed_time":0.8405953622,"remaining_time":1.078572131},
{"learn":[0.1272856748],"iteration":438,"passed_time":0.8423200125,"remaining_time":1.07640439},
{"learn":[0.1270929972],"iteration":439,"passed_time":0.84381057,"remaining_time":1.073940725},
{"learn":[0.1268825089],"iteration":440,"passed_time":0.8452046395,"remaining_time":1.071359169},
{"learn":[0.1266096256],"iteration":441,"passed_time":0.8467319585,"remaining_time":1.068951206},
{"learn":[0.1264265555],"iteration":442,"passed_time":0.8482339448,"remaining_time":1.066515366},
{"learn":[0.1262430792],"iteration":443,"passed_time":0.8496182116,"remaining_time":1.063936319},
{"learn":[0.1259565177],"iteration":444,"passed_time":0.8509390257,"remaining_time":1.061283504},
{"learn":[0.1257359187],"iteration":445,"passed_time":0.8522228003,"remaining_time":1.058590653},
{"learn":[0.1254706383],"iteration":446,"passed_time":0.8541791566,"remaining_time":1.056736183},
{"learn":[0.1251772951],"iteration":447,"passed_time":0.8557909748,"remaining_time":1.054456737},
{"learn":[0.1249159089],"iteration":448,"passed_time":0.8572708741,"remaining_time":1.052018378},
{"learn":[0.1245533714],"iteration":449,"passed_time":0.8587534098,"remaining_time":1.049587501},
{"learn":[0.124316295],"iteration":450,"passed_time":0.8602693466,"remaining_time":1.047201488},
{"learn":[0.1239507375],"iteration":451,"passed_time":0.8618887898,"remaining_time":1.044944816},
{"learn":[0.1236667456],"iteration":452,"passed_time":0.8634392948,"remaining_time":1.042607714},
{"learn":[0.1233786477],"iteration":453,"passed_time":0.8649102201,"remaining_time":1.04017837},
{"learn":[0.1231087755],"iteration":454,"passed_time":0.8664207266,"remaining_time":1.037800651},
{"learn":[0.1228895364],"iteration":455,"passed_time":0.8682789603,"remaining_time":1.035841567},
{"learn":[0.1227545208],"iteration":456,"passed_time":0.8697422316,"remaining_time":1.033413636},
{"learn":[0.122579292],"iteration":457,"passed_time":0.8711314582,"remaining_time":1.030902293},
{"learn":[0.1224873507],"iteration":458,"passed_time":0.8724570601,"remaining_time":1.028320849},
{"learn":[0.1222698512],"iteration":459,"passed_time":0.8743081131,"remaining_time":1.026361698},
{"learn":[0.1219959259],"iteration":460,"passed_time":0.8757988048,"remaining_time":1.023981683},
{"learn":[0.1216675529],"iteration":461,"passed_time":0.8771115707,"remaining_time":1.021398323},
{"learn":[0.1213841968],"iteration":462,"passed_time":0.8784772589,"remaining_time":1.018881832},
{"learn":[0.1212621971],"iteration":463,"passed_time":0.8800170724,"remaining_time":1.016571446},
{"learn":[0.1210742527],"iteration":464,"passed_time":0.8817225813,"remaining_time":1.014455013},
{"learn":[0.1208374765],"iteration":465,"passed_time":0.8832521504,"remaining_time":1.01213873},
{"learn":[0.1206935247],"iteration":466,"passed_time":0.8846449401,"remaining_time":1.009669707},
{"learn":[0.1206068816],"iteration":467,"passed_time":0.8862314959,"remaining_time":1.007425547},
{"learn":[0.1203575929],"iteration":468,"passed_time":0.8879029403,"remaining_time":1.005280301},
{"learn":[0.1202293855],"iteration":469,"passed_time":0.8894301288,"remaining_time":1.002974401},
{"learn":[0.1200838619],"iteration":470,"passed_time":0.8908567234,"remaining_time":1.000558825},
{"learn":[0.1198283037],"iteration":471,"passed_time":0.8923609019,"remaining_time":0.9982342292},
{"learn":[0.1196037398],"iteration":472,"passed_time":0.8942832975,"remaining_time":0.9963790651},
{"learn":[0.1194975111],"iteration":473,"passed_time":0.8956243547,"remaining_time":0.9938785033},
{"learn":[0.1193975696],"iteration":474,"passed_time":0.8971771057,"remaining_time":0.991616801},
{"learn":[0.1192805326],"iteration":475,"passed_time":0.8984727402,"remaining_time":0.9890750333},
{"learn":[0.1190069516],"iteration":476,"passed_time":0.9000860554,"remaining_time":0.9868868071},
{"learn":[0.1187744406],"iteration":477,"passed_time":0.9014610747,"remaining_time":0.9844407552},
{"learn":[0.1184279742],"iteration":478,"passed_time":0.9027676575,"remaining_time":0.9819247381},
{"learn":[0.1182123202],"iteration":479,"passed_time":0.9040895634,"remaining_time":0.9794303603},
{"learn":[0.1179428542],"iteration":480,"passed_time":0.9054515802,"remaining_time":0.9769841374},
{"learn":[0.117787211],"iteration":481,"passed_time":0.9072030594,"remaining_time":0.9749609642},
{"learn":[0.1174912541],"iteration":482,"passed_time":0.9086996216,"remaining_time":0.9726660545},
{"learn":[0.1171311979],"iteration":483,"passed_time":0.9100171849,"remaining_time":0.9701836103},
{"learn":[0.1169615322],"iteration":484,"passed_time":0.9113890694,"remaining_time":0.967763651},
{"learn":[0.1166973644],"iteration":485,"passed_time":0.9128784584,"remaining_time":0.9654722791},
{"learn":[0.1163830581],"iteration":486,"passed_time":0.9144198703,"remaining_time":0.963239001},
{"learn":[0.1161070488],"iteration":487,"passed_time":0.9157739656,"remaining_time":0.9608120295},
{"learn":[0.1160050498],"iteration":488,"passed_time":0.917110511,"remaining_time":0.9583711066},
{"learn":[0.1158067297],"iteration":489,"passed_time":0.918409597,"remaining_time":0.955895703},
{"learn":[0.1156155268],"iteration":490,"passed_time":0.9201253957,"remaining_time":0.9538570802},
{"learn":[0.1153068807],"iteration":491,"passed_time":0.9215124893,"remaining_time":0.9514803751},
{"learn":[0.1150884982],"iteration":492,"passed_time":0.9227880341,"remaining_time":0.9489929681},
{"learn":[0.1148196856],"iteration":493,"passed_time":0.9241068817,"remaining_time":0.9465548222},
{"learn":[0.1145702115],"iteration":494,"passed_time":0.9253728893,"remaining_time":0.9440672911},
{"learn":[0.1143525353],"iteration":495,"passed_time":0.9272070742,"remaining_time":0.942162027},
{"learn":[0.114202676],"iteration":496,"passed_time":0.9285959233,"remaining_time":0.9398063369},
{"learn":[0.1141400161],"iteration":497,"passed_time":0.9299332195,"remaining_time":0.9374025626},
{"learn":[0.1139615553],"iteration":498,"passed_time":0.9312795789,"remaining_time":0.9350121624},
{"learn":[0.1137403559],"iteration":499,"passed_time":0.9326573404,"remaining_time":0.9326573404},
{"learn":[0.1135731097],"iteration":500,"passed_time":0.9341529001,"remaining_time":0.9304237468},
{"learn":[0.1134038501],"iteration":501,"passed_time":0.9357414156,"remaining_time":0.9282853087},
{"learn":[0.1131578198],"iteration":502,"passed_time":0.93729155,"remaining_time":0.9261111339},
{"learn":[0.1130074395],"iteration":503,"passed_time":0.9387308264,"remaining_time":0.9238303371},
{"learn":[0.1127869995],"iteration":504,"passed_time":0.9405811071,"remaining_time":0.9219557386},
{"learn":[0.1126098633],"iteration":505,"passed_time":0.9423810772,"remaining_time":0.9200321189},
{"learn":[0.1124179275],"iteration":506,"passed_time":0.9438080283,"remaining_time":0.9177462681},
{"learn":[0.112288943],"iteration":507,"passed_time":0.9452441241,"remaining_time":0.9154726557},
{"learn":[0.1120825344],"iteration":508,"passed_time":0.9469482679,"remaining_time":0.9134609029},
{"learn":[0.1118660503],"iteration":509,"passed_time":0.9482960822,"remaining_time":0.9111080006},
{"learn":[0.1115700139],"iteration":510,"passed_time":0.9496575805,"remaining_time":0.9087721269},
{"learn":[0.1113597287],"iteration":511,"passed_time":0.9510271598,"remaining_time":0.9064477617},
{"learn":[0.1111338845],"iteration":512,"passed_time":0.9525421051,"remaining_time":0.9042651174},
{"learn":[0.1110101541],"iteration":513,"passed_time":0.9540236894,"remaining_time":0.9020535274},
{"learn":[0.1107193364],"iteration":514,"passed_time":0.9555180717,"remaining_time":0.8998568248},
{"learn":[0.1105112146],"iteration":515,"passed_time":0.9571913605,"remaining_time":0.8978306559},
{"learn":[0.1103536906],"iteration":516,"passed_time":0.9586863281,"remaining_time":0.8956392581},
{"learn":[0.1101314933],"iteration":517,"passed_time":0.9604761311,"remaining_time":0.8937248942},
{"learn":[0.1098583539],"iteration":518,"passed_time":0.9618641288,"remaining_time":0.8914386242},
{"learn":[0.1096267877],"iteration":519,"passed_time":0.9632516351,"remaining_time":0.8891553555},
{"learn":[0.1093957159],"iteration":520,"passed_time":0.9645307157,"remaining_time":0.8867758404},
{"learn":[0.1092577687],"iteration":521,"passed_time":0.9660168025,"remaining_time":0.8845900989},
{"learn":[0.1091087129],"iteration":522,"passed_time":0.9675293163,"remaining_time":0.8824311355},
{"learn":[0.1089809912],"iteration":523,"passed_time":0.9690254229,"remaining_time":0.8802597353},
{"learn":[0.1088912134],"iteration":524,"passed_time":0.9703391156,"remaining_time":0.8779258665},
{"learn":[0.1086091819],"iteration":525,"passed_time":0.9720286706,"remaining_time":0.8759345814},
{"learn":[0.1085371441],"iteration":526,"passed_time":0.9737096287,"remaining_time":0.8739367256},
{"learn":[0.1084246459],"iteration":527,"passed_time":0.9750409178,"remaining_time":0.8716274871},
{"learn":[0.1083762557],"iteration":528,"passed_time":0.9763748035,"remaining_time":0.8693242579},
{"learn":[0.1082902926],"iteration":529,"passed_time":0.9776536265,"remaining_time":0.8669758575},
{"learn":[0.1081049884],"iteration":530,"passed_time":0.9791706027,"remaining_time":0.8648418318},
{"learn":[0.1079134588],"iteration":531,"passed_time":0.9807414399,"remaining_time":0.8627575073},
{"learn":[0.1077336735],"iteration":532,"passed_time":0.9820923659,"remaining_time":0.8604824294},
{"learn":[0.1075597692],"iteration":533,"passed_time":0.9833732239,"remaining_time":0.8581496673},
{"learn":[0.10736031],"iteration":534,"passed_time":0.9847134653,"remaining_time":0.8558724512},
{"learn":[0.1072056647],"iteration":535,"passed_time":0.986570827,"remaining_time":0.8540463876},
{"learn":[0.107039116],"iteration":536,"passed_time":0.9880659214,"remaining_time":0.8519078614},
{"learn":[0.1069240217],"iteration":537,"passed_time":0.9894085279,"remaining_time":0.8496407805},
{"learn":[0.1068522312],"iteration":538,"passed_time":0.990826451,"remaining_time":0.8474415471},
{"learn":[0.1066185457],"iteration":539,"passed_time":0.9922860256,"remaining_time":0.8452806885},
{"learn":[0.1064820996],"iteration":540,"passed_time":0.9938214699,"remaining_time":0.8431867924},
{"learn":[0.1064220093],"iteration":541,"passed_time":0.995166906,"remaining_time":0.8409343966},
{"learn":[0.1061167364],"iteration":542,"passed_time":0.9965453466,"remaining_time":0.8387131186},
{"learn":[0.1058869274],"iteration":543,"passed_time":0.9978680368,"remaining_time":0.8364482073},
{"learn":[0.105669675],"iteration":544,"passed_time":0.9993735759,"remaining_time":0.8343394074},
{"learn":[0.1056018317],"iteration":545,"passed_time":1.001432175,"remaining_time":0.8326926873},
{"learn":[0.1054937751],"iteration":546,"passed_time":1.003192107,"remaining_time":0.8307971198},
{"learn":[0.1052710657],"iteration":547,"passed_time":1.004630149,"remaining_time":0.8286365459},
{"learn":[0.1050613545],"iteration":548,"passed_time":1.006402354,"remaining_time":0.8267531179},
{"learn":[0.104854884],"iteration":549,"passed_time":1.008037873,"remaining_time":0.8247582596},
{"learn":[0.1047169456],"iteration":550,"passed_time":1.009553957,"remaining_time":0.8226673802},
{"learn":[0.104669253],"iteration":551,"passed_time":1.011050573,"remaining_time":0.820562784},
{"learn":[0.1045225815],"iteration":552,"passed_time":1.012683695,"remaining_time":0.8185707265},
{"learn":[0.1043417542],"iteration":553,"passed_time":1.014234027,"remaining_time":0.816513314},
{"learn":[0.1041146561],"iteration":554,"passed_time":1.015695684,"remaining_time":0.8143866296},
{"learn":[0.1038557777],"iteration":555,"passed_time":1.017214428,"remaining_time":0.8123079247},
{"learn":[0.1037173801],"iteration":556,"passed_time":1.018641161,"remaining_time":0.8101580509},
{"learn":[0.1036047494],"iteration":557,"passed_time":1.02047679,"remaining_time":0.8083346613},
{"learn":[0.10337366],"iteration":558,"passed_time":1.021854915,"remaining_time":0.8061502997},
{"learn":[0.1032694004],"iteration":559,"passed_time":1.023157159,"remaining_time":0.8039091961},
{"learn":[0.1030220809],"iteration":560,"passed_time":1.024469595,"remaining_time":0.8016794158},
{"learn":[0.1028741642],"iteration":561,"passed_time":1.026109802,"remaining_time":0.7997083507},
{"learn":[0.1027878567],"iteration":562,"passed_time":1.027894416,"remaining_time":0.7978505501},
{"learn":[0.1027341419],"iteration":563,"passed_time":1.029615794,"remaining_time":0.7959441248},
{"learn":[0.1024419378],"iteration":564,"passed_time":1.031073306,"remaining_time":0.7938351999},
{"learn":[0.1022882726],"iteration":565,"passed_time":1.032758357,"remaining_time":0.7919030515},
{"learn":[0.1020120868],"iteration":566,"passed_time":1.034592491,"remaining_time":0.7900856239},
{"learn":[0.1019794676],"iteration":567,"passed_time":1.036020035,"remaining_time":0.7879588998},
{"learn":[0.1017298522],"iteration":568,"passed_time":1.037355987,"remaining_time":0.7857652556},
{"learn":[0.1016528518],"iteration":569,"passed_time":1.038725034,"remaining_time":0.7835995873},
{"learn":[0.1014100887],"iteration":570,"passed_time":1.040456346,"remaining_time":0.7817088835},
{"learn":[0.1013283288],"iteration":571,"passed_time":1.04186271,"remaining_time":0.7795755946},
{"learn":[0.1010676137],"iteration":572,"passed_time":1.043257386,"remaining_time":0.7774361322},
{"learn":[0.1008081436],"iteration":573,"passed_time":1.044660891,"remaining_time":0.775305818},
{"learn":[0.1006630968],"iteration":574,"passed_time":1.046207582,"remaining_time":0.7732838653},
{"learn":[0.1005199309],"iteration":575,"passed_time":1.047590494,"remaining_time":0.7711430028},
{"learn":[0.1003230413],"iteration":576,"passed_time":1.048964516,"remaining_time":0.7689982503},
{"learn":[0.1000842783],"iteration":577,"passed_time":1.050300696,"remaining_time":0.7668285359},
{"learn":[0.09987488499],"iteration":578,"passed_time":1.051969697,"remaining_time":0.7649036999},
{"learn":[0.09966497068],"iteration":579,"passed_time":1.053421369,"remaining_time":0.7628223709},
{"learn":[0.09955778828],"iteration":580,"passed_time":1.054792025,"remaining_time":0.7606847825},
{"learn":[0.09944747995],"iteration":581,"passed_time":1.056180787,"remaining_time":0.7585628332},
{"learn":[0.09935378145],"iteration":582,"passed_time":1.0576318,"remaining_time":0.7564879258},
{"learn":[0.09924742028],"iteration":583,"passed_time":1.07516101,"remaining_time":0.7658681168},
{"learn":[0.0990496035],"iteration":584,"passed_time":1.076706501,"remaining_time":0.7638174323},
{"learn":[0.09894323349],"iteration":585,"passed_time":1.078092188,"remaining_time":0.7616555733},
{"learn":[0.09887474555],"iteration":586,"passed_time":1.079689062,"remaining_time":0.7596449447},
{"learn":[0.09865179768],"iteration":587,"passed_time":1.08113336,"remaining_time":0.7575288172},
{"learn":[0.09837878192],"iteration":588,"passed_time":1.082630085,"remaining_time":0.7554515535},
{"learn":[0.09833567231],"iteration":589,"passed_time":1.084033821,"remaining_time":0.7533116384},
{"learn":[0.09823084761],"iteration":590,"passed_time":1.085535348,"remaining_time":0.7512418903},
{"learn":[0.09817756547],"iteration":591,"passed_time":1.087335698,"remaining_time":0.7493800082},
{"learn":[0.09789515425],"iteration":592,"passed_time":1.088715036,"remaining_time":0.7472293758},
{"learn":[0.09769857371],"iteration":593,"passed_time":1.090102253,"remaining_time":0.7450867253},
{"learn":[0.09756257799],"iteration":594,"passed_time":1.091447238,"remaining_time":0.7429178679},
{"learn":[0.09738993645],"iteration":595,"passed_time":1.093278113,"remaining_time":0.741081137},
{"learn":[0.09724505742],"iteration":596,"passed_time":1.094702603,"remaining_time":0.7389700986},
{"learn":[0.09708854887],"iteration":597,"passed_time":1.096091193,"remaining_time":0.7368372233},
{"learn":[0.09678527161],"iteration":598,"passed_time":1.097423869,"remaining_time":0.7346694014},
{"learn":[0.0965922232],"iteration":599,"passed_time":1.098850532,"remaining_time":0.7325670213},
{"learn":[0.09634960139],"iteration":600,"passed_time":1.10062813,"remaining_time":0.7306998732},
{"learn":[0.09610578749],"iteration":601,"passed_time":1.102082309,"remaining_time":0.7286192011},
{"learn":[0.09603057084],"iteration":602,"passed_time":1.103414625,"remaining_time":0.726460375},
{"learn":[0.09589122843],"iteration":603,"passed_time":1.104891983,"remaining_time":0.7243993797},
{"learn":[0.09579677052],"iteration":604,"passed_time":1.10695553,"remaining_time":0.7227230317},
{"learn":[0.09564332609],"iteration":605,"passed_time":1.108598221,"remaining_time":0.7207717809},
{"learn":[0.09553616135],"iteration":606,"passed_time":1.110246896,"remaining_time":0.7188254205},
{"learn":[0.09539288945],"iteration":607,"passed_time":1.111680388,"remaining_time":0.7167413025},
{"learn":[0.09528938046],"iteration":608,"passed_time":1.113670725,"remaining_time":0.7150168364},
{"learn":[0.09513038176],"iteration":609,"passed_time":1.115039602,"remaining_time":0.7128941718},
{"learn":[0.09512205477],"iteration":610,"passed_time":1.116384066,"remaining_time":0.7107584317},
{"learn":[0.09502734961],"iteration":611,"passed_time":1.117709918,"remaining_time":0.7086134775},
{"learn":[0.09482880875],"iteration":612,"passed_time":1.119332275,"remaining_time":0.7066583859},
{"learn":[0.09469311326],"iteration":613,"passed_time":1.120763924,"remaining_time":0.7045844861},
{"learn":[0.09458016466],"iteration":614,"passed_time":1.122065859,"remaining_time":0.7024314727},
{"learn":[0.09446628888],"iteration":615,"passed_time":1.12336074,"remaining_time":0.7002768249},
{"learn":[0.09429491008],"iteration":616,"passed_time":1.124689702,"remaining_time":0.6981461195},
{"learn":[0.0942156933],"iteration":617,"passed_time":1.126548394,"remaining_time":0.6963454471},
{"learn":[0.09410179103],"iteration":618,"passed_time":1.127980522,"remaining_time":0.6942820338},
{"learn":[0.09390641142],"iteration":619,"passed_time":1.129274322,"remaining_time":0.692135875},
{"learn":[0.09373899742],"iteration":620,"passed_time":1.130600937,"remaining_time":0.6900124879},
{"learn":[0.09370201605],"iteration":621,"passed_time":1.132013851,"remaining_time":0.687944109},
{"learn":[0.09357394112],"iteration":622,"passed_time":1.134196072,"remaining_time":0.6863433692},
{"learn":[0.09341877478],"iteration":623,"passed_time":1.135909206,"remaining_time":0.6844581114},
{"learn":[0.09327985622],"iteration":624,"passed_time":1.137304059,"remaining_time":0.6823824353},
{"learn":[0.09316062044],"iteration":625,"passed_time":1.138815928,"remaining_time":0.6803788452},
{"learn":[0.09307282942],"iteration":626,"passed_time":1.140396236,"remaining_time":0.6784175378},
{"learn":[0.09297711761],"iteration":627,"passed_time":1.141746247,"remaining_time":0.6763210251},
{"learn":[0.09280848503],"iteration":628,"passed_time":1.143081025,"remaining_time":0.6742179018},
{"learn":[0.09262480559],"iteration":629,"passed_time":1.144391492,"remaining_time":0.6721029398},
{"learn":[0.09244995647],"iteration":630,"passed_time":1.146208435,"remaining_time":0.6702867078},
{"learn":[0.09236349883],"iteration":631,"passed_time":1.147784579,"remaining_time":0.6683302609},
{"learn":[0.09223552103],"iteration":632,"passed_time":1.149351801,"remaining_time":0.6663698438},
{"learn":[0.09214805674],"iteration":633,"passed_time":1.150753264,"remaining_time":0.6643149758},
{"learn":[0.09203116982],"iteration":634,"passed_time":1.152264235,"remaining_time":0.6623251114},
{"learn":[0.0918836417],"iteration":635,"passed_time":1.153710527,"remaining_time":0.6602997356},
{"learn":[0.09175159313],"iteration":636,"passed_time":1.155225616,"remaining_time":0.6583153825},
{"learn":[0.09149077204],"iteration":637,"passed_time":1.156637391,"remaining_time":0.6562738803},
{"learn":[0.09137719649],"iteration":638,"passed_time":1.158096245,"remaining_time":0.654260946},
{"learn":[0.09124676387],"iteration":639,"passed_time":1.159669991,"remaining_time":0.6523143697},
{"learn":[0.09114792612],"iteration":640,"passed_time":1.161217708,"remaining_time":0.6503543793},
{"learn":[0.09102440763],"iteration":641,"passed_time":1.162528709,"remaining_time":0.6482636724},
{"learn":[0.09079911974],"iteration":642,"passed_time":1.163910238,"remaining_time":0.6462145487},
{"learn":[0.09066536691],"iteration":643,"passed_time":1.165277312,"remaining_time":0.6441595077},
{"learn":[0.09052756981],"iteration":644,"passed_time":1.166888582,"remaining_time":0.6422410027},
{"learn":[0.09032929385],"iteration":645,"passed_time":1.168294965,"remaining_time":0.6402111728},
{"learn":[0.09025022719],"iteration":646,"passed_time":1.169776716,"remaining_time":0.6382243905},
{"learn":[0.09005294906],"iteration":647,"passed_time":1.171294839,"remaining_time":0.636258925},
{"learn":[0.08995508265],"iteration":648,"passed_time":1.172773157,"remaining_time":0.63427331},
{"learn":[0.08986305307],"iteration":649,"passed_time":1.174207897,"remaining_time":0.6322657907},
{"learn":[0.08974317268],"iteration":650,"passed_time":1.175565348,"remaining_time":0.6302185966},
{"learn":[0.08964952716],"iteration":651,"passed_time":1.176872346,"remaining_time":0.6281465894},
{"learn":[0.08962879358],"iteration":652,"passed_time":1.17845265,"remaining_time":0.6262221585},
{"learn":[0.08945019157],"iteration":653,"passed_time":1.179991521,"remaining_time":0.6242768597},
{"learn":[0.08929269402],"iteration":654,"passed_time":1.181507227,"remaining_time":0.6223206006},
{"learn":[0.08920143269],"iteration":655,"passed_time":1.182842275,"remaining_time":0.6202709489},
{"learn":[0.08908840462],"iteration":656,"passed_time":1.184217762,"remaining_time":0.6182445853},
{"learn":[0.08901031812],"iteration":657,"passed_time":1.186194443,"remaining_time":0.6165326739},
{"learn":[0.08887812826],"iteration":658,"passed_time":1.187591641,"remaining_time":0.6145201055},
{"learn":[0.08873356713],"iteration":659,"passed_time":1.188922161,"remaining_time":0.6124750524},
{"learn":[0.08858147374],"iteration":660,"passed_time":1.190243434,"remaining_time":0.6104274191},
{"learn":[0.08838342737],"iteration":661,"passed_time":1.19165687,"remaining_time":0.6084290365},
{"learn":[0.08831406523],"iteration":662,"passed_time":1.193320192,"remaining_time":0.606559434},
{"learn":[0.0882084458],"iteration":663,"passed_time":1.194789597,"remaining_time":0.604592326},
{"learn":[0.08807696237],"iteration":664,"passed_time":1.196136133,"remaining_time":0.6025648188},
{"learn":[0.08798556858],"iteration":665,"passed_time":1.197419778,"remaining_time":0.6005078165},
{"learn":[0.08786703039],"iteration":666,"passed_time":1.199084126,"remaining_time":0.5986431995},
{"learn":[0.08776754803],"iteration":667,"passed_time":1.200541899,"remaining_time":0.5966765128},
{"learn":[0.08763247949],"iteration":668,"passed_time":1.201836788,"remaining_time":0.5946307575},
{"learn":[0.08758302971],"iteration":669,"passed_time":1.203202966,"remaining_time":0.5926223562},
{"learn":[0.0874179999],"iteration":670,"passed_time":1.20454423,"remaining_time":0.5906036536},
{"learn":[0.0871980985],"iteration":671,"passed_time":1.206310699,"remaining_time":0.5887945079},
{"learn":[0.08709633792],"iteration":672,"passed_time":1.207847975,"remaining_time":0.5868741275},
{"learn":[0.08685685087],"iteration":673,"passed_time":1.209225252,"remaining_time":0.584877496},
{"learn":[0.08681088907],"iteration":674,"passed_time":1.210585405,"remaining_time":0.5828744542},
{"learn":[0.08667234138],"iteration":675,"passed_time":1.212235346,"remaining_time":0.5810122073},
{"learn":[0.08664967396],"iteration":676,"passed_time":1.213587068,"remaining_time":0.5790083058},
{"learn":[0.08648293107],"iteration":677,"passed_time":1.214895067,"remaining_time":0.5769855627},
{"learn":[0.08646044908],"iteration":678,"passed_time":1.216197404,"remaining_time":0.5749622485},
{"learn":[0.08633850239],"iteration":679,"passed_time":1.217483668,"remaining_time":0.5729334908},
{"learn":[0.08619114205],"iteration":680,"passed_time":1.21912823,"remaining_time":0.5710747508},
{"learn":[0.08606846244],"iteration":681,"passed_time":1.220445479,"remaining_time":0.5690640208},
{"learn":[0.08596609257],"iteration":682,"passed_time":1.221802109,"remaining_time":0.5670735996},
{"learn":[0.08582977012],"iteration":683,"passed_time":1.223358226,"remaining_time":0.5651771921},
{"learn":[0.08569424241],"iteration":684,"passed_time":1.224828283,"remaining_time":0.5632422032},
{"learn":[0.08562600171],"iteration":685,"passed_time":1.226636694,"remaining_time":0.5614634431},
{"learn":[0.08534632789],"iteration":686,"passed_time":1.228270365,"remaining_time":0.5596049845},
{"learn":[0.08517507271],"iteration":687,"passed_time":1.22978629,"remaining_time":0.5576937825},
{"learn":[0.08498500895],"iteration":688,"passed_time":1.231155772,"remaining_time":0.555717627},
{"learn":[0.08492547494],"iteration":689,"passed_time":1.232889356,"remaining_time":0.5539068122},
{"learn":[0.08470802837],"iteration":690,"passed_time":1.234249589,"remaining_time":0.5519292664},
{"learn":[0.08459868254],"iteration":691,"passed_time":1.235595345,"remaining_time":0.5499470609},
{"learn":[0.08442235876],"iteration":692,"passed_time":1.236983951,"remaining_time":0.5479856754},
{"learn":[0.08422676722],"iteration":693,"passed_time":1.238647512,"remaining_time":0.5461471738},
{"learn":[0.08419909301],"iteration":694,"passed_time":1.240204682,"remaining_time":0.5442624866},
{"learn":[0.08415673397],"iteration":695,"passed_time":1.241562559,"remaining_time":0.5422916923},
{"learn":[0.0839558619],"iteration":696,"passed_time":1.242880037,"remaining_time":0.540305095},
{"learn":[0.08380534914],"iteration":697,"passed_time":1.244236726,"remaining_time":0.5383373802},
{"learn":[0.0836632605],"iteration":698,"passed_time":1.245988646,"remaining_time":0.5365416058},
{"learn":[0.08346103739],"iteration":699,"passed_time":1.247399917,"remaining_time":0.5345999644},
{"learn":[0.08339827149],"iteration":700,"passed_time":1.248812266,"remaining_time":0.5326602962},
{"learn":[0.08331577866],"iteration":701,"passed_time":1.250227432,"remaining_time":0.530723326},
{"learn":[0.08308279073],"iteration":702,"passed_time":1.251967272,"remaining_time":0.5289250067},
{"learn":[0.08291288658],"iteration":703,"passed_time":1.253577739,"remaining_time":0.5270724583},
{"learn":[0.08283185076],"iteration":704,"passed_time":1.25504947,"remaining_time":0.5251625441},
{"learn":[0.08266892257],"iteration":705,"passed_time":1.256489207,"remaining_time":0.5232405478},
{"learn":[0.08248890771],"iteration":706,"passed_time":1.25787519,"remaining_time":0.521297639},
{"learn":[0.08231904772],"iteration":707,"passed_time":1.259733872,"remaining_time":0.519551258},
{"learn":[0.08212702363],"iteration":708,"passed_time":1.261190861,"remaining_time":0.5176396903},
{"learn":[0.08204068078],"iteration":709,"passed_time":1.262572338,"remaining_time":0.5156985604},
{"learn":[0.08201623846],"iteration":710,"passed_time":1.263939239,"remaining_time":0.5137530801},
{"learn":[0.08189792103],"iteration":711,"passed_time":1.265644967,"remaining_time":0.5119462787},
{"learn":[0.08171314663],"iteration":712,"passed_time":1.26720612,"remaining_time":0.510081566},
{"learn":[0.08159702796],"iteration":713,"passed_time":1.268722678,"remaining_time":0.5081998402},
{"learn":[0.08152748037],"iteration":714,"passed_time":1.270078761,"remaining_time":0.5062551705},
{"learn":[0.08138932122],"iteration":715,"passed_time":1.271646666,"remaining_time":0.5043961637},
{"learn":[0.08123405774],"iteration":716,"passed_time":1.273185076,"remaining_time":0.502526327},
{"learn":[0.08109366452],"iteration":717,"passed_time":1.274582938,"remaining_time":0.5006022123},
{"learn":[0.08105166753],"iteration":718,"passed_time":1.275942879,"remaining_time":0.4986647414},
{"learn":[0.08094861772],"iteration":719,"passed_time":1.277308824,"remaining_time":0.4967312094},
{"learn":[0.08075749433],"iteration":720,"passed_time":1.279016505,"remaining_time":0.494931491},
{"learn":[0.08060750255],"iteration":721,"passed_time":1.280330913,"remaining_time":0.4929806009},
{"learn":[0.08050033781],"iteration":722,"passed_time":1.281779824,"remaining_time":0.4910830032},
{"learn":[0.08036043026],"iteration":723,"passed_time":1.283182788,"remaining_time":0.4891691292},
{"learn":[0.08024247487],"iteration":724,"passed_time":1.28466626,"remaining_time":0.4872872021},
{"learn":[0.08011384364],"iteration":725,"passed_time":1.28618363,"remaining_time":0.4854191662},
{"learn":[0.07996326906],"iteration":726,"passed_time":1.287840392,"remaining_time":0.4836044387},
{"learn":[0.07983670411],"iteration":727,"passed_time":1.289187622,"remaining_time":0.4816744963},
{"learn":[0.07968913184],"iteration":728,"passed_time":1.290548667,"remaining_time":0.4797512878},
{"learn":[0.07966734745],"iteration":729,"passed_time":1.292345813,"remaining_time":0.4779909172},
{"learn":[0.0795287821],"iteration":730,"passed_time":1.293863945,"remaining_time":0.4761277717},
{"learn":[0.07951145702],"iteration":731,"passed_time":1.295189662,"remaining_time":0.4741951223},
{"learn":[0.07938762947],"iteration":732,"passed_time":1.296578797,"remaining_time":0.4722872289},
{"learn":[0.07929743661],"iteration":733,"passed_time":1.298179468,"remaining_time":0.4704574093},
{"learn":[0.07926342222],"iteration":734,"passed_time":1.299621209,"remaining_time":0.4685709122},
{"learn":[0.07914678256],"iteration":735,"passed_time":1.300949058,"remaining_time":0.4666447708},
{"learn":[0.07897774378],"iteration":736,"passed_time":1.302325521,"remaining_time":0.4647376011},
{"learn":[0.07885242392],"iteration":737,"passed_time":1.303672496,"remaining_time":0.4628214011},
{"learn":[0.07872314806],"iteration":738,"passed_time":1.305276517,"remaining_time":0.4609975249},
{"learn":[0.07859021646],"iteration":739,"passed_time":1.306688365,"remaining_time":0.459106723},
{"learn":[0.07845209263],"iteration":740,"passed_time":1.308022605,"remaining_time":0.4571900874},
{"learn":[0.07827461207],"iteration":741,"passed_time":1.309341011,"remaining_time":0.455269516},
{"learn":[0.07813964067],"iteration":742,"passed_time":1.31066277,"remaining_time":0.4533517254},
{"learn":[0.07799184764],"iteration":743,"passed_time":1.312440651,"remaining_time":0.4515924821},
{"learn":[0.07776225938],"iteration":744,"passed_time":1.313805609,"remaining_time":0.4496918528},
{"learn":[0.07774493429],"iteration":745,"passed_time":1.315217409,"remaining_time":0.4478086084},
{"learn":[0.07760514153],"iteration":746,"passed_time":1.316629733,"remaining_time":0.4459268038},
{"learn":[0.07740870229],"iteration":747,"passed_time":1.318158873,"remaining_time":0.4440856097},
{"learn":[0.07735954391],"iteration":748,"passed_time":1.319655346,"remaining_time":0.4422343014},
{"learn":[0.07728921926],"iteration":749,"passed_time":1.321140758,"remaining_time":0.4403802527},
{"learn":[0.07716004054],"iteration":750,"passed_time":1.322449287,"remaining_time":0.4384685385},
{"learn":[0.07698933283],"iteration":751,"passed_time":1.323794257,"remaining_time":0.4365704465},
{"learn":[0.07696421941],"iteration":752,"passed_time":1.325600561,"remaining_time":0.4348251509},
{"learn":[0.07688221225],"iteration":753,"passed_time":1.326984353,"remaining_time":0.4329418445},
{"learn":[0.07677532125],"iteration":754,"passed_time":1.328421182,"remaining_time":0.4310770724},
{"learn":[0.07660069289],"iteration":755,"passed_time":1.329773945,"remaining_time":0.4291862998},
{"learn":[0.07649300717],"iteration":756,"passed_time":1.331243649,"remaining_time":0.4273344869},
{"learn":[0.07644196793],"iteration":757,"passed_time":1.332858013,"remaining_time":0.4255298671},
{"learn":[0.076355369],"iteration":758,"passed_time":1.334412461,"remaining_time":0.4237067236},
{"learn":[0.07620105037],"iteration":759,"passed_time":1.335792012,"remaining_time":0.4218290563},
{"learn":[0.07603800738],"iteration":760,"passed_time":1.337108877,"remaining_time":0.4199330113},
{"learn":[0.07589970695],"iteration":761,"passed_time":1.338780684,"remaining_time":0.4181493476},
{"learn":[0.07578902774],"iteration":762,"passed_time":1.340200353,"remaining_time":0.4162876588},
{"learn":[0.07566159743],"iteration":763,"passed_time":1.341560721,"remaining_time":0.4144088091},
{"learn":[0.07549638218],"iteration":764,"passed_time":1.343354217,"remaining_time":0.4126643675},
{"learn":[0.07537471807],"iteration":765,"passed_time":1.345024655,"remaining_time":0.4108822052},
{"learn":[0.0752579901],"iteration":766,"passed_time":1.346510798,"remaining_time":0.4090443494},
{"learn":[0.07503865383],"iteration":767,"passed_time":1.34800652,"remaining_time":0.4072103028},
{"learn":[0.07488515642],"iteration":768,"passed_time":1.349445259,"remaining_time":0.4053600192},
{"learn":[0.07474503694],"iteration":769,"passed_time":1.350864422,"remaining_time":0.4035049572},
{"learn":[0.07455522043],"iteration":770,"passed_time":1.352591497,"remaining_time":0.4017424809},
{"learn":[0.07438813315],"iteration":771,"passed_time":1.354100048,"remaining_time":0.3999155581},
{"learn":[0.07436645472],"iteration":772,"passed_time":1.355484305,"remaining_time":0.3980529588},
{"learn":[0.07434190644],"iteration":773,"passed_time":1.356848908,"remaining_time":0.3961858567},
{"learn":[0.07418187459],"iteration":774,"passed_time":1.358849228,"remaining_time":0.3945046146},
{"learn":[0.07411794309],"iteration":775,"passed_time":1.360429363,"remaining_time":0.3927012595},
{"learn":[0.07402574575],"iteration":776,"passed_time":1.362058291,"remaining_time":0.3909124826},
{"learn":[0.07393048869],"iteration":777,"passed_time":1.363580877,"remaining_time":0.389093772},
{"learn":[0.07389192228],"iteration":778,"passed_time":1.365917367,"remaining_time":0.3875067241},
{"learn":[0.0737473479],"iteration":779,"passed_time":1.367359257,"remaining_time":0.3856654313},
{"learn":[0.07360877814],"iteration":780,"passed_time":1.368963977,"remaining_time":0.3838708206},
{"learn":[0.07345725872],"iteration":781,"passed_time":1.37041583,"remaining_time":0.3820340806},
{"learn":[0.07341727504],"iteration":782,"passed_time":1.372097344,"remaining_time":0.3802619714},
{"learn":[0.07323631534],"iteration":783,"passed_time":1.373553039,"remaining_time":0.3784278781},
{"learn":[0.07310412548],"iteration":784,"passed_time":1.374877468,"remaining_time":0.3765587969},
{"learn":[0.07307610688],"iteration":785,"passed_time":1.37625959,"remaining_time":0.3747068094},
{"learn":[0.07304164657],"iteration":786,"passed_time":1.377747057,"remaining_time":0.3728845276},
{"learn":[0.07285384779],"iteration":787,"passed_time":1.379390647,"remaining_time":0.371105098},
{"learn":[0.07277528003],"iteration":788,"passed_time":1.380874786,"remaining_time":0.3692833711},
{"learn":[0.07267767412],"iteration":789,"passed_time":1.382266927,"remaining_time":0.3674380438},
{"learn":[0.07249531039],"iteration":790,"passed_time":1.38363019,"remaining_time":0.3655862323},
{"learn":[0.07238699772],"iteration":791,"passed_time":1.38537509,"remaining_time":0.3638358823},
{"learn":[0.07231101725],"iteration":792,"passed_time":1.387204454,"remaining_time":0.3621075939},
{"learn":[0.07216731707],"iteration":793,"passed_time":1.388684366,"remaining_time":0.3602883871},
{"learn":[0.07202377584],"iteration":794,"passed_time":1.390096237,"remaining_time":0.3584524887},
{"learn":[0.07186057391],"iteration":795,"passed_time":1.391835585,"remaining_time":0.3567015822},
{"learn":[0.07184012289],"iteration":796,"passed_time":1.393310742,"remaining_time":0.3548834136},
{"learn":[0.07181867847],"iteration":797,"passed_time":1.394851594,"remaining_time":0.3530827343},
{"learn":[0.07172744804],"iteration":798,"passed_time":1.396205385,"remaining_time":0.3512356475},
{"learn":[0.07164242091],"iteration":799,"passed_time":1.39780688,"remaining_time":0.3494517201},
{"learn":[0.07158514305],"iteration":800,"passed_time":1.399409952,"remaining_time":0.3476686398},
{"learn":[0.07145552723],"iteration":801,"passed_time":1.400843774,"remaining_time":0.3458442236},
{"learn":[0.07130265677],"iteration":802,"passed_time":1.402506704,"remaining_time":0.3440769871},
{"learn":[0.0711697031],"iteration":803,"passed_time":1.403812598,"remaining_time":0.3422229717},
{"learn":[0.07105137684],"iteration":804,"passed_time":1.405115827,"remaining_time":0.3403696723},
{"learn":[0.07096025237],"iteration":805,"passed_time":1.406477878,"remaining_time":0.3385318961},
{"learn":[0.07077677162],"iteration":806,"passed_time":1.408179998,"remaining_time":0.3367766291},
{"learn":[0.07066411001],"iteration":807,"passed_time":1.409636437,"remaining_time":0.3349631138},
{"learn":[0.07054993841],"iteration":808,"passed_time":1.410966338,"remaining_time":0.3331206065},
{"learn":[0.07036036474],"iteration":809,"passed_time":1.412472118,"remaining_time":0.3313206203},
{"learn":[0.0702019091],"iteration":810,"passed_time":1.413949212,"remaining_time":0.3295146745},
{"learn":[0.07016177089],"iteration":811,"passed_time":1.41566642,"remaining_time":0.3277651317},
{"learn":[0.0701303173],"iteration":812,"passed_time":1.417122577,"remaining_time":0.3259556235},
{"learn":[0.0700575599],"iteration":813,"passed_time":1.418638511,"remaining_time":0.3241606425},
{"learn":[0.07003151046],"iteration":814,"passed_time":1.419956918,"remaining_time":0.3223215089},
{"learn":[0.06992152885],"iteration":815,"passed_time":1.421562188,"remaining_time":0.3205483365},
{"learn":[0.06976362511],"iteration":816,"passed_time":1.422879033,"remaining_time":0.3187109707},
{"learn":[0.06967655376],"iteration":817,"passed_time":1.42424137,"remaining_time":0.3168849992},
{"learn":[0.06954474802],"iteration":818,"passed_time":1.425578617,"remaining_time":0.3150546149},
{"learn":[0.06943073096],"iteration":819,"passed_time":1.427183818,"remaining_time":0.3132842528},
{"learn":[0.06936196486],"iteration":820,"passed_time":1.428884404,"remaining_time":0.3115350893},
{"learn":[0.06927680969],"iteration":821,"passed_time":1.430590919,"remaining_time":0.309787328},
{"learn":[0.06909947925],"iteration":822,"passed_time":1.432013561,"remaining_time":0.3079786152},
{"learn":[0.06905838295],"iteration":823,"passed_time":1.433430483,"remaining_time":0.3061696178},
{"learn":[0.06902609048],"iteration":824,"passed_time":1.435116584,"remaining_time":0.3044186693},
{"learn":[0.06900741436],"iteration":825,"passed_time":1.436597807,"remaining_time":0.3026247196},
{"learn":[0.06882558929],"iteration":826,"passed_time":1.438142864,"remaining_time":0.3008448797},
{"learn":[0.06868883857],"iteration":827,"passed_time":1.43967258,"remaining_time":0.29906242},
{"learn":[0.06855483408],"iteration":828,"passed_time":1.441571288,"remaining_time":0.2973566831},
{"learn":[0.06842737728],"iteration":829,"passed_time":1.442965531,"remaining_time":0.2955471569},
{"learn":[0.06841605681],"iteration":830,"passed_time":1.444267342,"remaining_time":0.2937198325},
{"learn":[0.06832465861],"iteration":831,"passed_time":1.445573487,"remaining_time":0.2918946464},
{"learn":[0.06825314628],"iteration":832,"passed_time":1.446978745,"remaining_time":0.2900905767},
{"learn":[0.06816430445],"iteration":833,"passed_time":1.44868517,"remaining_time":0.2883474079},
{"learn":[0.06813944269],"iteration":834,"passed_time":1.450276737,"remaining_time":0.2865816307},
{"learn":[0.06801276295],"iteration":835,"passed_time":1.451712406,"remaining_time":0.2847856874},
{"learn":[0.06784564036],"iteration":836,"passed_time":1.45307239,"remaining_time":0.2829758656},
{"learn":[0.06771344609],"iteration":837,"passed_time":1.454653688,"remaining_time":0.2812099016},
{"learn":[0.06767916238],"iteration":838,"passed_time":1.456041258,"remaining_time":0.279407202},
{"learn":[0.06754223506],"iteration":839,"passed_time":1.457558268,"remaining_time":0.2776301462},
{"learn":[0.06738080802],"iteration":840,"passed_time":1.458883591,"remaining_time":0.2758174684},
{"learn":[0.06722452022],"iteration":841,"passed_time":1.460452693,"remaining_time":0.274051693},
{"learn":[0.06712113486],"iteration":842,"passed_time":1.462070988,"remaining_time":0.2722955457},
{"learn":[0.06707501411],"iteration":843,"passed_time":1.463417483,"remaining_time":0.2704894873},
{"learn":[0.06695276278],"iteration":844,"passed_time":1.464809689,"remaining_time":0.2686929015},
{"learn":[0.06685826514],"iteration":845,"passed_time":1.466211643,"remaining_time":0.2668990462},
{"learn":[0.06672419001],"iteration":846,"passed_time":1.46771289,"remaining_time":0.2651240521},
{"learn":[0.06664960914],"iteration":847,"passed_time":1.469065007,"remaining_time":0.263322973},
{"learn":[0.06658721853],"iteration":848,"passed_time":1.470393042,"remaining_time":0.2615186682},
{"learn":[0.06645753649],"iteration":849,"passed_time":1.471769236,"remaining_time":0.2597239829},
{"learn":[0.06635409373],"iteration":850,"passed_time":1.473342415,"remaining_time":0.2579647707},
{"learn":[0.06623702579],"iteration":851,"passed_time":1.474989605,"remaining_time":0.2562188516},
{"learn":[0.0660579337],"iteration":852,"passed_time":1.476535605,"remaining_time":0.2544557256},
{"learn":[0.06589772083],"iteration":853,"passed_time":1.477904184,"remaining_time":0.2526627762},
{"learn":[0.06576191937],"iteration":854,"passed_time":1.479224153,"remaining_time":0.2508625756},
{"learn":[0.06564584043],"iteration":855,"passed_time":1.481153833,"remaining_time":0.2491660653},
{"learn":[0.06550681591],"iteration":856,"passed_time":1.482546316,"remaining_time":0.2473793736},
{"learn":[0.06547353003],"iteration":857,"passed_time":1.483874831,"remaining_time":0.2455830141},
{"learn":[0.06534805121],"iteration":858,"passed_time":1.485175439,"remaining_time":0.2437831628},
{"learn":[0.06518273883],"iteration":859,"passed_time":1.486704274,"remaining_time":0.242021626},
{"learn":[0.06508725219],"iteration":860,"passed_time":1.488513336,"remaining_time":0.2403058696},
{"learn":[0.0649998188],"iteration":861,"passed_time":1.490209539,"remaining_time":0.2385718287},
{"learn":[0.06483842267],"iteration":862,"passed_time":1.491824605,"remaining_time":0.2368249953},
{"learn":[0.06477178468],"iteration":863,"passed_time":1.493573234,"remaining_time":0.2350994905},
{"learn":[0.06474369102],"iteration":864,"passed_time":1.495294609,"remaining_time":0.2333696789},
{"learn":[0.06472488686],"iteration":865,"passed_time":1.496686786,"remaining_time":0.2315889484},
{"learn":[0.06463032299],"iteration":866,"passed_time":1.498157692,"remaining_time":0.2298211914},
{"learn":[0.06452499054],"iteration":867,"passed_time":1.499593651,"remaining_time":0.2280488041},
{"learn":[0.0644170973],"iteration":868,"passed_time":1.501621881,"remaining_time":0.2263664746},
{"learn":[0.06428142389],"iteration":869,"passed_time":1.503173928,"remaining_time":0.2246121962},
{"learn":[0.06425362605],"iteration":870,"passed_time":1.504606015,"remaining_time":0.2228406154},
{"learn":[0.06414376365],"iteration":871,"passed_time":1.505954003,"remaining_time":0.2210574684},
{"learn":[0.06399767487],"iteration":872,"passed_time":1.507705882,"remaining_time":0.2193340745},
{"learn":[0.063918957],"iteration":873,"passed_time":1.509451246,"remaining_time":0.2176096763},
{"learn":[0.06386876989],"iteration":874,"passed_time":1.510888584,"remaining_time":0.2158412263},
{"learn":[0.06381888301],"iteration":875,"passed_time":1.512367679,"remaining_time":0.2140794432},
{"learn":[0.06370932085],"iteration":876,"passed_time":1.5141946,"remaining_time":0.2123670875},
{"learn":[0.0636037853],"iteration":877,"passed_time":1.515605547,"remaining_time":0.2105966705},
{"learn":[0.06343324979],"iteration":878,"passed_time":1.517028068,"remaining_time":0.2088286647},
{"learn":[0.06332785553],"iteration":879,"passed_time":1.518517962,"remaining_time":0.2070706312},
{"learn":[0.0631877493],"iteration":880,"passed_time":1.520103125,"remaining_time":0.2053260748},
{"learn":[0.06307645197],"iteration":881,"passed_time":1.521532239,"remaining_time":0.2035610025},
{"learn":[0.06296083662],"iteration":882,"passed_time":1.522939965,"remaining_time":0.2017938572},
{"learn":[0.06285462115],"iteration":883,"passed_time":1.524347421,"remaining_time":0.2000274896},
{"learn":[0.06274092639],"iteration":884,"passed_time":1.525828551,"remaining_time":0.1982715066},
{"learn":[0.06262847229],"iteration":885,"passed_time":1.527477993,"remaining_time":0.1965378005},
{"learn":[0.06260279373],"iteration":886,"passed_time":1.529144018,"remaining_time":0.1948063969},
{"learn":[0.06250591631],"iteration":887,"passed_time":1.530766731,"remaining_time":0.1930696778},
{"learn":[0.06239951981],"iteration":888,"passed_time":1.532147084,"remaining_time":0.1913029542},
{"learn":[0.06238829648],"iteration":889,"passed_time":1.534048936,"remaining_time":0.1896015539},
{"learn":[0.06229327343],"iteration":890,"passed_time":1.535643852,"remaining_time":0.1878621547},
{"learn":[0.06223509047],"iteration":891,"passed_time":1.537108859,"remaining_time":0.1861073506},
{"learn":[0.06213418201],"iteration":892,"passed_time":1.538560221,"remaining_time":0.1843515607},
{"learn":[0.06208955359],"iteration":893,"passed_time":1.540231041,"remaining_time":0.1826224724},
{"learn":[0.06201890663],"iteration":894,"passed_time":1.541985396,"remaining_time":0.1809033146},
{"learn":[0.06191043501],"iteration":895,"passed_time":1.54337526,"remaining_time":0.1791417712},
{"learn":[0.06182071456],"iteration":896,"passed_time":1.544740914,"remaining_time":0.1773782766},
{"learn":[0.06180822408],"iteration":897,"passed_time":1.546397314,"remaining_time":0.1756486927},
{"learn":[0.06169512978],"iteration":898,"passed_time":1.548153436,"remaining_time":0.173930475},
{"learn":[0.06167763692],"iteration":899,"passed_time":1.549421475,"remaining_time":0.1721579416},
{"learn":[0.06161458845],"iteration":900,"passed_time":1.550744366,"remaining_time":0.1703925552},
{"learn":[0.06148268117],"iteration":901,"passed_time":1.552077129,"remaining_time":0.1686292224},
{"learn":[0.06146131621],"iteration":902,"passed_time":1.553781268,"remaining_time":0.1669067364},
{"learn":[0.0613336519],"iteration":903,"passed_time":1.555113712,"remaining_time":0.1651448189},
{"learn":[0.06122675207],"iteration":904,"passed_time":1.556458903,"remaining_time":0.1633851887},
{"learn":[0.06120953736],"iteration":905,"passed_time":1.557815721,"remaining_time":0.1616276797},
{"learn":[0.06110704828],"iteration":906,"passed_time":1.559156118,"remaining_time":0.1598693704},
{"learn":[0.06105157623],"iteration":907,"passed_time":1.561309318,"remaining_time":0.1581943362},
{"learn":[0.06095895061],"iteration":908,"passed_time":1.563137992,"remaining_time":0.1564857615},
{"learn":[0.06087892144],"iteration":909,"passed_time":1.564922939,"remaining_time":0.1547725984},
{"learn":[0.06077852073],"iteration":910,"passed_time":1.56676,"remaining_time":0.1530643688},
{"learn":[0.06076468362],"iteration":911,"passed_time":1.568767655,"remaining_time":0.1513723175},
{"learn":[0.06068681346],"iteration":912,"passed_time":1.570431175,"remaining_time":0.1496467823},
{"learn":[0.06067490136],"iteration":913,"passed_time":1.572216619,"remaining_time":0.1479328547},
{"learn":[0.06057257564],"iteration":914,"passed_time":1.575180369,"remaining_time":0.146328231},
{"learn":[0.06056320226],"iteration":915,"passed_time":1.577294288,"remaining_time":0.1446427076},
{"learn":[0.06043201023],"iteration":916,"passed_time":1.579544161,"remaining_time":0.1429685554},
{"learn":[0.06029753773],"iteration":917,"passed_time":1.581510836,"remaining_time":0.1412678524},
{"learn":[0.06021226777],"iteration":918,"passed_time":1.583300482,"remaining_time":0.1395509674},
{"learn":[0.06005768423],"iteration":919,"passed_time":1.585335477,"remaining_time":0.1378552589},
{"learn":[0.06003692415],"iteration":920,"passed_time":1.587242436,"remaining_time":0.1361478311},
{"learn":[0.05993417016],"iteration":921,"passed_time":1.589088476,"remaining_time":0.1344348169},
{"learn":[0.05984503693],"iteration":922,"passed_time":1.590974039,"remaining_time":0.1327248115},
{"learn":[0.0597426803],"iteration":923,"passed_time":1.592918899,"remaining_time":0.1310193034},
{"learn":[0.0596396614],"iteration":924,"passed_time":1.595074972,"remaining_time":0.1293304031},
{"learn":[0.0596175547],"iteration":925,"passed_time":1.596991424,"remaining_time":0.1276213449},
{"learn":[0.05955308897],"iteration":926,"passed_time":1.598806718,"remaining_time":0.1259038732},
{"learn":[0.05945237478],"iteration":927,"passed_time":1.601362352,"remaining_time":0.1242436308},
{"learn":[0.05930769885],"iteration":928,"passed_time":1.603269168,"remaining_time":0.122531874},
{"learn":[0.05923304734],"iteration":929,"passed_time":1.605110611,"remaining_time":0.1208147771},
{"learn":[0.05914138865],"iteration":930,"passed_time":1.607072538,"remaining_time":0.1191063428},
{"learn":[0.05901701362],"iteration":931,"passed_time":1.609071983,"remaining_time":0.1174001018},
{"learn":[0.05900851885],"iteration":932,"passed_time":1.611324544,"remaining_time":0.1157114088},
{"learn":[0.05890687748],"iteration":933,"passed_time":1.61360508,"remaining_time":0.1140234853},
{"learn":[0.05880112118],"iteration":934,"passed_time":1.615279649,"remaining_time":0.1122921681},
{"learn":[0.05866145646],"iteration":935,"passed_time":1.616987525,"remaining_time":0.1105632496},
{"learn":[0.05855823446],"iteration":936,"passed_time":1.618622181,"remaining_time":0.1088294529},
{"learn":[0.05844292817],"iteration":937,"passed_time":1.621222408,"remaining_time":0.1071596901},
{"learn":[0.05834983896],"iteration":938,"passed_time":1.622922427,"remaining_time":0.1054294654},
{"learn":[0.05823308009],"iteration":939,"passed_time":1.624865087,"remaining_time":0.1037147928},
{"learn":[0.05812818033],"iteration":940,"passed_time":1.627590374,"remaining_time":0.1020487057},
{"learn":[0.05806961766],"iteration":941,"passed_time":1.629738154,"remaining_time":0.100344812},
{"learn":[0.05798482895],"iteration":942,"passed_time":1.631799517,"remaining_time":0.09863475342},
{"learn":[0.05784126564],"iteration":943,"passed_time":1.633798078,"remaining_time":0.09692022497},
{"learn":[0.05771591045],"iteration":944,"passed_time":1.635680653,"remaining_time":0.09519834486},
{"learn":[0.05763136016],"iteration":945,"passed_time":1.637554973,"remaining_time":0.09347565384},
{"learn":[0.05752092821],"iteration":946,"passed_time":1.639930815,"remaining_time":0.09178071086},
{"learn":[0.05737589465],"iteration":947,"passed_time":1.642122045,"remaining_time":0.090074205},
{"learn":[0.05730007754],"iteration":948,"passed_time":1.64380492,"remaining_time":0.08833935818},
{"learn":[0.05718608256],"iteration":949,"passed_time":1.645412655,"remaining_time":0.08660066604},
{"learn":[0.0571079784],"iteration":950,"passed_time":1.647327754,"remaining_time":0.08487808619},
{"learn":[0.05695512118],"iteration":951,"passed_time":1.649050098,"remaining_time":0.08314538311},
{"learn":[0.05680033013],"iteration":952,"passed_time":1.650901087,"remaining_time":0.08141904628},
{"learn":[0.05676131778],"iteration":953,"passed_time":1.652787907,"remaining_time":0.0796941758},
{"learn":[0.05666132768],"iteration":954,"passed_time":1.654628672,"remaining_time":0.07796679607},
{"learn":[0.05657809752],"iteration":955,"passed_time":1.656347728,"remaining_time":0.07623357744},
{"learn":[0.05648705253],"iteration":956,"passed_time":1.658182159,"remaining_time":0.07450557246},
{"learn":[0.0564670916],"iteration":957,"passed_time":1.660334683,"remaining_time":0.07279129091},
{"learn":[0.05632773152],"iteration":958,"passed_time":1.662100864,"remaining_time":0.07105957815},
{"learn":[0.0562613187],"iteration":959,"passed_time":1.664363787,"remaining_time":0.06934849113},
{"learn":[0.0561848923],"iteration":960,"passed_time":1.66659229,"remaining_time":0.06763485881},
{"learn":[0.05607757745],"iteration":961,"passed_time":1.66846392,"remaining_time":0.06590605921},
{"learn":[0.05595772355],"iteration":962,"passed_time":1.670004334,"remaining_time":0.06416423712},
{"learn":[0.05593663675],"iteration":963,"passed_time":1.671640182,"remaining_time":0.06242639683},
{"learn":[0.05580566548],"iteration":964,"passed_time":1.673516777,"remaining_time":0.06069749968},
{"learn":[0.05566828339],"iteration":965,"passed_time":1.6752599,"remaining_time":0.05896359896},
{"learn":[0.05560036059],"iteration":966,"passed_time":1.677024726,"remaining_time":0.05723041981},
{"learn":[0.055481063],"iteration":967,"passed_time":1.679369413,"remaining_time":0.05551634423},
{"learn":[0.05542090646],"iteration":968,"passed_time":1.681039557,"remaining_time":0.05377938728},
{"learn":[0.05539825228],"iteration":969,"passed_time":1.682844936,"remaining_time":0.0520467506},
{"learn":[0.05531035971],"iteration":970,"passed_time":1.684644799,"remaining_time":0.05031379934},
{"learn":[0.05516861103],"iteration":971,"passed_time":1.686676292,"remaining_time":0.04858738291},
{"learn":[0.05504071712],"iteration":972,"passed_time":1.688409349,"remaining_time":0.04685205798},
{"learn":[0.05502423975],"iteration":973,"passed_time":1.690117729,"remaining_time":0.04511607901},
{"learn":[0.05494787958],"iteration":974,"passed_time":1.69232414,"remaining_time":0.04339292667},
{"learn":[0.05484823386],"iteration":975,"passed_time":1.694057165,"remaining_time":0.04165714341},
{"learn":[0.05475791737],"iteration":976,"passed_time":1.695651079,"remaining_time":0.0399180909},
{"learn":[0.05468295239],"iteration":977,"passed_time":1.697267205,"remaining_time":0.03817983488},
{"learn":[0.05458355833],"iteration":978,"passed_time":1.699198231,"remaining_time":0.0364485831},
{"learn":[0.05451462004],"iteration":979,"passed_time":1.700827497,"remaining_time":0.03471076524},
{"learn":[0.05447770931],"iteration":980,"passed_time":1.702481109,"remaining_time":0.03297364024},
{"learn":[0.05439105299],"iteration":981,"passed_time":1.704065691,"remaining_time":0.03123542},
{"learn":[0.05429781808],"iteration":982,"passed_time":1.706092654,"remaining_time":0.02950516289},
{"learn":[0.05419981038],"iteration":983,"passed_time":1.707905799,"remaining_time":0.027770826},
{"learn":[0.05408761236],"iteration":984,"passed_time":1.709370107,"remaining_time":0.02603101686},
{"learn":[0.05396185098],"iteration":985,"passed_time":1.711059894,"remaining_time":0.02429496807},
{"learn":[0.05391662651],"iteration":986,"passed_time":1.712796429,"remaining_time":0.02255962874},
{"learn":[0.05380567798],"iteration":987,"passed_time":1.714474849,"remaining_time":0.02082358116},
{"learn":[0.05367166025],"iteration":988,"passed_time":1.71584202,"remaining_time":0.01908418829},
{"learn":[0.05357717585],"iteration":989,"passed_time":1.717319888,"remaining_time":0.01734666554},
{"learn":[0.05348476657],"iteration":990,"passed_time":1.719459957,"remaining_time":0.01561568074},
{"learn":[0.05345911891],"iteration":991,"passed_time":1.721156013,"remaining_time":0.01388029042},
{"learn":[0.05337914273],"iteration":992,"passed_time":1.722899481,"remaining_time":0.01214531356},
{"learn":[0.05326194233],"iteration":993,"passed_time":1.724491345,"remaining_time":0.0104094045},
{"learn":[0.0531943595],"iteration":994,"passed_time":1.726222286,"remaining_time":0.008674483851},
{"learn":[0.05314537331],"iteration":995,"passed_time":1.728317576,"remaining_time":0.00694103444},
{"learn":[0.05311206977],"iteration":996,"passed_time":1.729965384,"remaining_time":0.00520551269},
{"learn":[0.05302555031],"iteration":997,"passed_time":1.731586705,"remaining_time":0.003470113638},
{"learn":[0.05292598406],"iteration":998,"passed_time":1.73324464,"remaining_time":0.00173497962},
{"learn":[0.05287641508],"iteration":999,"passed_time":1.734986185,"remaining_time":0}
]}